Workbook

Sheet 怎么用
A1: 90-C4 学生档案与积分总表 v2.4 2026-08-20
A3: 一、先把三个最容易懵的词说清楚
A4: 1）「文件名」——电脑里现在没有这个文件，Excel 也不是相册
A5: 贴完学号以后，紫色格子会出现「2401006.png」这种字。这不是一张已经画好的图，也不是网盘链接。它只是一张便签：以后你要给这个学生画卡通头像（用电脑生成，或自己画），保存图片时就把文件名叫成学号，比如 2401006.png。40 个人的头像才不会乱。现在还没画，所以你在电脑里、在这个 Excel 里，都找不到这个文件。正常，不用找、不用建文件夹。
A6: 2）「去每周积分里找总分」——不是现在去翻一份现成的分数
A7: 「学生档案」右边的 T_累计积分，会到旁边那张「每周积分」里，按学号把这个人各周的分加起来。现在还没上课，「每周积分」全是空的，所以这边显示 0。不是公式坏了，是还没开始记。它的用处：以后评奖、学生来换免点名卡、看谁领先，你看这一列就行，不用自己拿计算器加。
A8: 3）「文件名、累计积分、等级、红线自己跳出来」——就是公式自动算，你不用填
A9: 你只负责把学生填的题贴进左边（班级到第21题）。右边四列紫色格子是公式：有学号 → 出现 学号.png；有学号且每周积分开始有数 → 累计分会涨；有第18题 → 红线会写成「可正常使用 / 只用奖励风格 / ★形象不可公开」。不要往紫色格子里粘企业微信导出。T_备注是唯一要你手写的（班长、人缘好、缺课）。
A11: 二、积分平时怎么记（本周计算器在哪、G列到底是哪一列）
A12: 「本周计算器」就是本文件底下的一张表，和「每周积分」并排。不是另一个软件。点最底下的表名就能进去。
A13: 课堂上不是举手加分。用 90-B2 点名器：视频放完抽 3 个人，说「册子举起来」，写了 2 分、写好或愿意念 5 分、空白跳过不说话。下课点「导出成绩表」。打地鼠用 90-B1，一局 12 题，每题约 12 秒，游戏里会显示 60～140 分——那是游戏分，不会直接加进周分，计算器会折成 0 / 2 / 5。作业不是书后课后题，你不用一本一本改。只有项目结束的收集表、或最难的加分题收集表，才打三档：没写 0、写了跑题 2、写了切题 5。没有收集表的那一周，作业列空着。
A14: 每周做一次（比如周五）就这 5 步： 1. 打开本文件，点最底下「本周计算器」。 2. 点名器导出的表，找到最下面「本节汇总」（三列：姓名 / 组号 / 本节合计），贴到右边 S 列。 3. 打地鼠导出的表，连表头贴到中间 J 列。D 列会自己变成 0、2 或 5。 4. 如果这周有收集表，E、F 列手填 0 或 2 或 5；没有就空着。 5. 「本周计算器」里表头黄色、写着「本周合计 ← 复制这一列」的那一列，复制 → 打开「每周积分」→ 粘到正在记的那一周（第1周就粘第1周，第5周才粘第5周）→ 右键「粘贴数值」。 不要复制「每周积分」自己的 G 列。那一列表头是「第5周」。
... A69: A：说一句就行，不用专门讲岗位。桌签上已经写了「管钱的。库存现金、银行存款从这组过。」你说：你们这组叫出纳组，管钱的，以后填收付款凭证从你们这过。现在先坐一起。真正用上桌签的时候：打地鼠按组上台、填凭证组内互审、静默十五分讨论。点名加分、举册子还是个人的。

Sheet 学生档案
A1: 白格＝粘贴/手填；蓝格＝有下拉；紫格＝公式，不要往紫格里粘。紫色「T_卡通形象文件名」出现 2401006.png，不是说电脑里已经有这张图——以后画头像时用这个名字保存，现在不用找。紫色「T_累计积分」现在是 0 正常：上课以后每周往「每周积分」贴一次才会涨。AA列签名只有纸质才手写，企业微信不建。 记分：打开「本周计算器」（本文件另一张表），复制「本周合计」那一列，粘到「每周积分」正在记的那一周。不要复制每周积分的 G 列（那是第5周）。
A2: 班级 | B2: 学号 | C2: 姓名 | D2: 宿舍 | E2: 1_以前接触过会计吗 | F2: 2_自己数学怎么样 | G2: 3_希望这门课怎么上 | H2: 4_最担心这门课什么 | I2: 5_上课最想看到哪个动画 | J2: 6_还喜欢哪个动画 | K2: 7_喜欢的明星或主播 | L2: 8_外号是什么谁起的 | M2: 9_口头禅 | N2: 10_小动作或小习惯 | O2: 11_最怕上课被问到什么 | P2: 12_平时最爱做什么 | Q2: 13_三个词形容自己 | R2: 14_请同桌用三个词形容你 | S2: 15_舍友觉得你最搞笑的事 | T2: 16_想不想和喜欢的卡通同框 | U2: 17_如果被画进去最想搞懂哪件事 | V2: 18_能用你的照片画卡通吗 | W2: 19_什么奖励对你有用 | X2: 20_哪种惩罚你能接受还觉得好玩 | Y2: 21_想对老师说的话 | Z2: 填表日期 | AA2: 本人签名 | AB2: T_卡通形象文件名 | AC2: T_累计积分 | AD2: T_当前等级 | AE2: T_红线_形象 | AF2: T_备注
AB3: =IF(B3="","",B3&".png") | AC3: =IF(B3="","",IFERROR(INDEX(每周积分!$U:$U,MATCH(B3,每周积分!$A:$A,0)),0)) | AD3: =IF(AC3="","",IFERROR(INDEX(每周积分!$V:$V,MATCH(B3,每周积分!$A:$A,0)),"")) | AE3: =IF(TRIM(V3&"")="","",IF(OR(TRIM(V3)="不要用我的照片",TRIM(V3)="只给我自己看"),"★形象不可公开",IF(TRIM(V3)="可以但别画太丑","只用奖励风格","可正常使用")))
AB4: =IF(B4="","",B4&".png") | AC4: =IF(B4="","",IFERROR(INDEX(每周积分!$U:$U,MATCH(B4,每周积分!$A:$A,0)),0)) | AD4: =IF(AC4="","",IFERROR(INDEX(每周积分!$V:$V,MATCH(B4,每周积分!$A:$A,0)),"")) | AE4: =IF(TRIM(V4&"")="","",IF(OR(TRIM(V4)="不要用我的照片",TRIM(V4)="只给我自己看"),"★形象不可公开",IF(TRIM(V4)="可以但别画太丑","只用奖励风格","可正常使用")))
AB5: =IF(B5="","",B5&".png") | AC5: =IF(B5="","",IFERROR(INDEX(每周积分!$U:$U,MATCH(B5,每周积分!$A:$A,0)),0)) | AD5: =IF(AC5="","",IFERROR(INDEX(每周积分!$V:$V,MATCH(B5,每周积分!$A:$A,0)),"")) | AE5: =IF(TRIM(V5&"")="","",IF(OR(TRIM(V5)="不要用我的照片",TRIM(V5)="只给我自己看"),"★形象不可公开",IF(TRIM(V5)="可以但别画太丑","只用奖励风格","可正常使用")))
AB6: =IF(B6="","",B6&".png") | AC6: =IF(B6="","",IFERROR(INDEX(每周积分!$U:$U,MATCH(B6,每周积分!$A:$A,0)),0)) | AD6: =IF(AC6="","",IFERROR(INDEX(每周积分!$V:$V,MATCH(B6,每周积分!$A:$A,0)),"")) | AE6: =IF(TRIM(V6&"")="","",IF(OR(TRIM(V6)="不要用我的照片",TRIM(V6)="只给我自己看"),"★形象不可公开",IF(TRIM(V6)="可以但别画太丑","只用奖励风格","可正常使用")))
AB7: =IF(B7="","",B7&".png") | AC7: =IF(B7="","",IFERROR(INDEX(每周积分!$U:$U,MATCH(B7,每周积分!$A:$A,0)),0)) | AD7: =IF(AC7="","",IFERROR(INDEX(每周积分!$V:$V,MATCH(B7,每周积分!$A:$A,0)),"")) | AE7: =IF(TRIM(V7&"")="","",IF(OR(TRIM(V7)="不要用我的照片",TRIM(V7)="只给我自己看"),"★形象不可公开",IF(TRIM(V7)="可以但别画太丑","只用奖励风格","可正常使用")))
AB8: =IF(B8="","",B8&".png") | AC8: =IF(B8="","",IFERROR(INDEX(每周积分!$U:$U,MATCH(B8,每周积分!$A:$A,0)),0)) | AD8: =IF(AC8="","",IFERROR(INDEX(每周积分!$V:$V,MATCH(B8,每周积分!$A:$A,0)),"")) | AE8: =IF(TRIM(V8&"")="","",IF(OR(TRIM(V8)="不要用我的照片",TRIM(V8)="只给我自己看"),"★形象不可公开",IF(TRIM(V8)="可以但别画太丑","只用奖励风格","可正常使用")))
AB9: =IF(B9="","",B9&".png") | AC9: =IF(B9="","",IFERROR(INDEX(每周积分!$U:$U,MATCH(B9,每周积分!$A:$A,0)),0)) | AD9: =IF(AC9="","",IFERROR(INDEX(每周积分!$V:$V,MATCH(B9,每周积分!$A:$A,0)),"")) | AE9: =IF(TRIM(V9&"")="","",IF(OR(TRIM(V9)="不要用我的照片",TRIM(V9)="只给我自己看"),"★形象不可公开",IF(TRIM(V9)="可以但别画太丑","只用奖励风格","可正常使用")))
AB10: =IF(B10="","",B10&".png") | AC10: =IF(B10="","",IFERROR(INDEX(每周积分!$U:$U,MATCH(B10,每周积分!$A:$A,0)),0)) | AD10: =IF(AC10="","",IFERROR(INDEX(每周积分!$V:$V,MATCH(B10,每周积分!$A:$A,0)),"")) | AE10: =IF(TRIM(V10&"")="","",IF(OR(TRIM(V10)="不要用我的照片",TRIM(V10)="只给我自己看"),"★形象不可公开",IF(TRIM(V10)="可以但别画太丑","只用奖励风格","可正常使用")))
AB11: =IF(B11="","",B11&".png") | AC11: =IF(B11="","",IFERROR(INDEX(每周积分!$U:$U,MATCH(B11,每周积分!$A:$A,0)),0)) | AD11: =IF(AC11="","",IFERROR(INDEX(每周积分!$V:$V,MATCH(B11,每周积分!$A:$A,0)),"")) | AE11: =IF(TRIM(V11&"")="","",IF(OR(TRIM(V11)="不要用我的照片",TRIM(V11)="只给我自己看"),"★形象不可公开",IF(TRIM(V11)="可以但别画太丑","只用奖励风格","可正常使用")))
AB12: =IF(B12="","",B12&".png") | AC12: =IF(B12="","",IFERROR(INDEX(每周积分!$U:$U,MATCH(B12,每周积分!$A:$A,0)),0)) | AD12: =IF(AC12="","",IFERROR(INDEX(每周积分!$V:$V,MATCH(B12,每周积分!$A:$A,0)),"")) | AE12: =IF(TRIM(V12&"")="","",IF(OR(TRIM(V12)="不要用我的照片",TRIM(V12)="只给我自己看"),"★形象不可公开",IF(TRIM(V12)="可以但别画太丑","只用奖励风格","可正常使用")))
AB13: =IF(B13="","",B13&".png") | AC13: =IF(B13="","",IFERROR(INDEX(每周积分!$U:$U,MATCH(B13,每周积分!$A:$A,0)),0)) | AD13: =IF(AC13="","",IFERROR(INDEX(每周积分!$V:$V,MATCH(B13,每周积分!$A:$A,0)),"")) | AE13: =IF(TRIM(V13&"")="","",IF(OR(TRIM(V13)="不要用我的照片",TRIM(V13)="只给我自己看"),"★形象不可公开",IF(TRIM(V13)="可以但别画太丑","只用奖励风格","可正常使用")))
AB14: =IF(B14="","",B14&".png") | AC14: =IF(B14="","",IFERROR(INDEX(每周积分!$U:$U,MATCH(B14,每周积分!$A:$A,0)),0)) | AD14: =IF(AC14="","",IFERROR(INDEX(每周积分!$V:$V,MATCH(B14,每周积分!$A:$A,0)),"")) | AE14: =IF(TRIM(V14&"")="","",IF(OR(TRIM(V14)="不要用我的照片",TRIM(V14)="只给我自己看"),"★形象不可公开",IF(TRIM(V14)="可以但别画太丑","只用奖励风格","可正常使用")))
... AB52: =IF(B52="","",B52&".png") | AC52: =IF(B52="","",IFERROR(INDEX(每周积分!$U:$U,MATCH(B52,每周积分!$A:$A,0)),0)) | AD52: =IF(AC52="","",IFERROR(INDEX(每周积分!$V:$V,MATCH(B52,每周积分!$A:$A,0)),"")) | AE52: =IF(TRIM(V52&"")="","",IF(OR(TRIM(V52)="不要用我的照片",TRIM(V52)="只给我自己看"),"★形象不可公开",IF(TRIM(V52)="可以但别画太丑","只用奖励风格","可正常使用")))

Sheet 每周积分
A1: 现在这一张全是空的，正常——还没上课。「本周计算器」是本文件底下另一张表（和这一张并排），不是别的软件。每周五：打开「本周计算器」，把那张表里表头叫「本周合计」的那一列复制成数值，粘到这一张正在记的那一周下面——现在是第1周就粘「第1周」，到第5周才粘「第5周」。不要复制这一张的 G 列，G 列的表头是「第5周」，跟本周合计没关系。U 列累计、V 列等级会自己加。右上角 X1 填你正在记的是第几周。 | W1: 当前周次 → | X1: 1
A2: 学号 | B2: 姓名 | C2: 第1周 | D2: 第2周 | E2: 第3周 | F2: 第4周 | G2: 第5周 | H2: 第6周 | I2: 第7周 | J2: 第8周 | K2: 第9周 | L2: 第10周 | M2: 第11周 | N2: 第12周 | O2: 第13周 | P2: 第14周 | Q2: 第15周 | R2: 第16周 | S2: 第17周 | T2: 第18周 | U2: 累计 | V2: 当前等级
A3: =IF(学生档案!B3="","",学生档案!B3) | B3: =IF(学生档案!C3="","",学生档案!C3) | U3: =IF(A3="","",SUM(C3:T3)) | V3: =IF(U3="","",IF(U3>=80,"Lv5 CFO",IF(U3>=50,"Lv4 主管会计",IF(U3>=30,"Lv3 记账会计",IF(U3>=15,"Lv2 出纳","Lv1 实习生")))))
A4: =IF(学生档案!B4="","",学生档案!B4) | B4: =IF(学生档案!C4="","",学生档案!C4) | U4: =IF(A4="","",SUM(C4:T4)) | V4: =IF(U4="","",IF(U4>=80,"Lv5 CFO",IF(U4>=50,"Lv4 主管会计",IF(U4>=30,"Lv3 记账会计",IF(U4>=15,"Lv2 出纳","Lv1 实习生")))))
A5: =IF(学生档案!B5="","",学生档案!B5) | B5: =IF(学生档案!C5="","",学生档案!C5) | U5: =IF(A5="","",SUM(C5:T5)) | V5: =IF(U5="","",IF(U5>=80,"Lv5 CFO",IF(U5>=50,"Lv4 主管会计",IF(U5>=30,"Lv3 记账会计",IF(U5>=15,"Lv2 出纳","Lv1 实习生")))))
A6: =IF(学生档案!B6="","",学生档案!B6) | B6: =IF(学生档案!C6="","",学生档案!C6) | U6: =IF(A6="","",SUM(C6:T6)) | V6: =IF(U6="","",IF(U6>=80,"Lv5 CFO",IF(U6>=50,"Lv4 主管会计",IF(U6>=30,"Lv3 记账会计",IF(U6>=15,"Lv2 出纳","Lv1 实习生")))))
A7: =IF(学生档案!B7="","",学生档案!B7) | B7: =IF(学生档案!C7="","",学生档案!C7) | U7: =IF(A7="","",SUM(C7:T7)) | V7: =IF(U7="","",IF(U7>=80,"Lv5 CFO",IF(U7>=50,"Lv4 主管会计",IF(U7>=30,"Lv3 记账会计",IF(U7>=15,"Lv2 出纳","Lv1 实习生")))))
A8: =IF(学生档案!B8="","",学生档案!B8) | B8: =IF(学生档案!C8="","",学生档案!C8) | U8: =IF(A8="","",SUM(C8:T8)) | V8: =IF(U8="","",IF(U8>=80,"Lv5 CFO",IF(U8>=50,"Lv4 主管会计",IF(U8>=30,"Lv3 记账会计",IF(U8>=15,"Lv2 出纳","Lv1 实习生")))))
A9: =IF(学生档案!B9="","",学生档案!B9) | B9: =IF(学生档案!C9="","",学生档案!C9) | U9: =IF(A9="","",SUM(C9:T9)) | V9: =IF(U9="","",IF(U9>=80,"Lv5 CFO",IF(U9>=50,"Lv4 主管会计",IF(U9>=30,"Lv3 记账会计",IF(U9>=15,"Lv2 出纳","Lv1 实习生")))))
A10: =IF(学生档案!B10="","",学生档案!B10) | B10: =IF(学生档案!C10="","",学生档案!C10) | U10: =IF(A10="","",SUM(C10:T10)) | V10: =IF(U10="","",IF(U10>=80,"Lv5 CFO",IF(U10>=50,"Lv4 主管会计",IF(U10>=30,"Lv3 记账会计",IF(U10>=15,"Lv2 出纳","Lv1 实习生")))))
A11: =IF(学生档案!B11="","",学生档案!B11) | B11: =IF(学生档案!C11="","",学生档案!C11) | U11: =IF(A11="","",SUM(C11:T11)) | V11: =IF(U11="","",IF(U11>=80,"Lv5 CFO",IF(U11>=50,"Lv4 主管会计",IF(U11>=30,"Lv3 记账会计",IF(U11>=15,"Lv2 出纳","Lv1 实习生")))))
A12: =IF(学生档案!B12="","",学生档案!B12) | B12: =IF(学生档案!C12="","",学生档案!C12) | U12: =IF(A12="","",SUM(C12:T12)) | V12: =IF(U12="","",IF(U12>=80,"Lv5 CFO",IF(U12>=50,"Lv4 主管会计",IF(U12>=30,"Lv3 记账会计",IF(U12>=15,"Lv2 出纳","Lv1 实习生")))))
A13: =IF(学生档案!B13="","",学生档案!B13) | B13: =IF(学生档案!C13="","",学生档案!C13) | U13: =IF(A13="","",SUM(C13:T13)) | V13: =IF(U13="","",IF(U13>=80,"Lv5 CFO",IF(U13>=50,"Lv4 主管会计",IF(U13>=30,"Lv3 记账会计",IF(U13>=15,"Lv2 出纳","Lv1 实习生")))))
A14: =IF(学生档案!B14="","",学生档案!B14) | B14: =IF(学生档案!C14="","",学生档案!C14) | U14: =IF(A14="","",SUM(C14:T14)) | V14: =IF(U14="","",IF(U14>=80,"Lv5 CFO",IF(U14>=50,"Lv4 主管会计",IF(U14>=30,"Lv3 记账会计",IF(U14>=15,"Lv2 出纳","Lv1 实习生")))))
... A52: =IF(学生档案!B52="","",学生档案!B52) | B52: =IF(学生档案!C52="","",学生档案!C52) | U52: =IF(A52="","",SUM(C52:T52)) | V52: =IF(U52="","",IF(U52>=80,"Lv5 CFO",IF(U52>=50,"Lv4 主管会计",IF(U52>=30,"Lv3 记账会计",IF(U52>=15,"Lv2 出纳","Lv1 实习生")))))

Sheet 本周计算器
A1: 这张表就在本文件底下，点「本周计算器」进去。用处：把这一周三处的分加总，得出「本周合计」。①点名器 90-B2 导出的表，找到最下面「本节汇总」（姓名/组号/本节合计），贴到右边 S 列；②打地鼠 90-B1 导出的表贴到中间 J 列（含表头）。游戏里的 100 多分不会直接加进来，D 列会自动折成 0 / 2 / 5；③作业不是书后课后题。只有「项目结束的收集表」或「加分题收集表」才打分：没写 0、写了跑题 2、写了切题 5。没有收集表的那一周，E、F 列空着；④表头黄色的「本周合计 ← 复制这一列」，复制后到「每周积分」正在记的那一周，右键粘贴数值。不要粘到「每周积分」的 G 列——那是第5周。 | J1: 打地鼠成绩粘贴区（含表头。游戏分会折成 0/2/5，不会把 142 分加进周分） | S1: 点名器「本节汇总」粘贴区（只贴最下面那块：姓名,组号,本节合计）
A2: 学号 | B2: 姓名 | C2: 课堂分_90B2 | D2: 打地鼠（自动折成0/2/5） | E2: 作业1（收集表才填） | F2: 作业2（收集表才填） | G2: 本周合计 ← 复制这一列 | H2: 构成 | J2: 日期 | K2: 姓名 | L2: 难度 | M2: 得分 | N2: 答对 | O2: 答错 | P2: 用时秒 | Q2: 错题 | S2: 姓名 | T2: 组号 | U2: 本节合计
A3: =IF(每周积分!A3="","",每周积分!A3) | B3: =IF(每周积分!B3="","",每周积分!B3) | C3: =IF(B3="","",IFERROR(SUMIF($S$3:$S$200,B3,$U$3:$U$200),0)) | D3: =IF(B3="","",IFERROR(IF(SUMIF($K$3:$K$200,B3,$M$3:$M$200)<=0,0,IF(SUMIF($K$3:$K$200,B3,$M$3:$M$200)>=100,5,2)),0)) | G3: =IF(A3="","",SUM(C3:F3)) | H3: =IF(A3="","",CONCATENATE("课",C3," +鼠",D3," +作业",N(E3)+N(F3)))
A4: =IF(每周积分!A4="","",每周积分!A4) | B4: =IF(每周积分!B4="","",每周积分!B4) | C4: =IF(B4="","",IFERROR(SUMIF($S$3:$S$200,B4,$U$3:$U$200),0)) | D4: =IF(B4="","",IFERROR(IF(SUMIF($K$3:$K$200,B4,$M$3:$M$200)<=0,0,IF(SUMIF($K$3:$K$200,B4,$M$3:$M$200)>=100,5,2)),0)) | G4: =IF(A4="","",SUM(C4:F4)) | H4: =IF(A4="","",CONCATENATE("课",C4," +鼠",D4," +作业",N(E4)+N(F4)))
A5: =IF(每周积分!A5="","",每周积分!A5) | B5: =IF(每周积分!B5="","",每周积分!B5) | C5: =IF(B5="","",IFERROR(SUMIF($S$3:$S$200,B5,$U$3:$U$200),0)) | D5: =IF(B5="","",IFERROR(IF(SUMIF($K$3:$K$200,B5,$M$3:$M$200)<=0,0,IF(SUMIF($K$3:$K$200,B5,$M$3:$M$200)>=100,5,2)),0)) | G5: =IF(A5="","",SUM(C5:F5)) | H5: =IF(A5="","",CONCATENATE("课",C5," +鼠",D5," +作业",N(E5)+N(F5)))
A6: =IF(每周积分!A6="","",每周积分!A6) | B6: =IF(每周积分!B6="","",每周积分!B6) | C6: =IF(B6="","",IFERROR(SUMIF($S$3:$S$200,B6,$U$3:$U$200),0)) | D6: =IF(B6="","",IFERROR(IF(SUMIF($K$3:$K$200,B6,$M$3:$M$200)<=0,0,IF(SUMIF($K$3:$K$200,B6,$M$3:$M$200)>=100,5,2)),0)) | G6: =IF(A6="","",SUM(C6:F6)) | H6: =IF(A6="","",CONCATENATE("课",C6," +鼠",D6," +作业",N(E6)+N(F6)))
A7: =IF(每周积分!A7="","",每周积分!A7) | B7: =IF(每周积分!B7="","",每周积分!B7) | C7: =IF(B7="","",IFERROR(SUMIF($S$3:$S$200,B7,$U$3:$U$200),0)) | D7: =IF(B7="","",IFERROR(IF(SUMIF($K$3:$K$200,B7,$M$3:$M$200)<=0,0,IF(SUMIF($K$3:$K$200,B7,$M$3:$M$200)>=100,5,2)),0)) | G7: =IF(A7="","",SUM(C7:F7)) | H7: =IF(A7="","",CONCATENATE("课",C7," +鼠",D7," +作业",N(E7)+N(F7)))
A8: =IF(每周积分!A8="","",每周积分!A8) | B8: =IF(每周积分!B8="","",每周积分!B8) | C8: =IF(B8="","",IFERROR(SUMIF($S$3:$S$200,B8,$U$3:$U$200),0)) | D8: =IF(B8="","",IFERROR(IF(SUMIF($K$3:$K$200,B8,$M$3:$M$200)<=0,0,IF(SUMIF($K$3:$K$200,B8,$M$3:$M$200)>=100,5,2)),0)) | G8: =IF(A8="","",SUM(C8:F8)) | H8: =IF(A8="","",CONCATENATE("课",C8," +鼠",D8," +作业",N(E8)+N(F8)))
A9: =IF(每周积分!A9="","",每周积分!A9) | B9: =IF(每周积分!B9="","",每周积分!B9) | C9: =IF(B9="","",IFERROR(SUMIF($S$3:$S$200,B9,$U$3:$U$200),0)) | D9: =IF(B9="","",IFERROR(IF(SUMIF($K$3:$K$200,B9,$M$3:$M$200)<=0,0,IF(SUMIF($K$3:$K$200,B9,$M$3:$M$200)>=100,5,2)),0)) | G9: =IF(A9="","",SUM(C9:F9)) | H9: =IF(A9="","",CONCATENATE("课",C9," +鼠",D9," +作业",N(E9)+N(F9)))
A10: =IF(每周积分!A10="","",每周积分!A10) | B10: =IF(每周积分!B10="","",每周积分!B10) | C10: =IF(B10="","",IFERROR(SUMIF($S$3:$S$200,B10,$U$3:$U$200),0)) | D10: =IF(B10="","",IFERROR(IF(SUMIF($K$3:$K$200,B10,$M$3:$M$200)<=0,0,IF(SUMIF($K$3:$K$200,B10,$M$3:$M$200)>=100,5,2)),0)) | G10: =IF(A10="","",SUM(C10:F10)) | H10: =IF(A10="","",CONCATENATE("课",C10," +鼠",D10," +作业",N(E10)+N(F10)))
A11: =IF(每周积分!A11="","",每周积分!A11) | B11: =IF(每周积分!B11="","",每周积分!B11) | C11: =IF(B11="","",IFERROR(SUMIF($S$3:$S$200,B11,$U$3:$U$200),0)) | D11: =IF(B11="","",IFERROR(IF(SUMIF($K$3:$K$200,B11,$M$3:$M$200)<=0,0,IF(SUMIF($K$3:$K$200,B11,$M$3:$M$200)>=100,5,2)),0)) | G11: =IF(A11="","",SUM(C11:F11)) | H11: =IF(A11="","",CONCATENATE("课",C11," +鼠",D11," +作业",N(E11)+N(F11)))
A12: =IF(每周积分!A12="","",每周积分!A12) | B12: =IF(每周积分!B12="","",每周积分!B12) | C12: =IF(B12="","",IFERROR(SUMIF($S$3:$S$200,B12,$U$3:$U$200),0)) | D12: =IF(B12="","",IFERROR(IF(SUMIF($K$3:$K$200,B12,$M$3:$M$200)<=0,0,IF(SUMIF($K$3:$K$200,B12,$M$3:$M$200)>=100,5,2)),0)) | G12: =IF(A12="","",SUM(C12:F12)) | H12: =IF(A12="","",CONCATENATE("课",C12," +鼠",D12," +作业",N(E12)+N(F12)))
A13: =IF(每周积分!A13="","",每周积分!A13) | B13: =IF(每周积分!B13="","",每周积分!B13) | C13: =IF(B13="","",IFERROR(SUMIF($S$3:$S$200,B13,$U$3:$U$200),0)) | D13: =IF(B13="","",IFERROR(IF(SUMIF($K$3:$K$200,B13,$M$3:$M$200)<=0,0,IF(SUMIF($K$3:$K$200,B13,$M$3:$M$200)>=100,5,2)),0)) | G13: =IF(A13="","",SUM(C13:F13)) | H13: =IF(A13="","",CONCATENATE("课",C13," +鼠",D13," +作业",N(E13)+N(F13)))
A14: =IF(每周积分!A14="","",每周积分!A14) | B14: =IF(每周积分!B14="","",每周积分!B14) | C14: =IF(B14="","",IFERROR(SUMIF($S$3:$S$200,B14,$U$3:$U$200),0)) | D14: =IF(B14="","",IFERROR(IF(SUMIF($K$3:$K$200,B14,$M$3:$M$200)<=0,0,IF(SUMIF($K$3:$K$200,B14,$M$3:$M$200)>=100,5,2)),0)) | G14: =IF(A14="","",SUM(C14:F14)) | H14: =IF(A14="","",CONCATENATE("课",C14," +鼠",D14," +作业",N(E14)+N(F14)))
... A52: =IF(每周积分!A52="","",每周积分!A52) | B52: =IF(每周积分!B52="","",每周积分!B52) | C52: =IF(B52="","",IFERROR(SUMIF($S$3:$S$200,B52,$U$3:$U$200),0)) | D52: =IF(B52="","",IFERROR(IF(SUMIF($K$3:$K$200,B52,$M$3:$M$200)<=0,0,IF(SUMIF($K$3:$K$200,B52,$M$3:$M$200)>=100,5,2)),0)) | G52: =IF(A52="","",SUM(C52:F52)) | H52: =IF(A52="","",CONCATENATE("课",C52," +鼠",D52," +作业",N(E52)+N(F52)))

Sheet 本周之星
A1: 进步最大跟每周积分 X1 走。讲题/帮扶手选。出镜前：T_红线带星号的不要画；第16题选「这次先不参加」的不要画。
A2: 周次 | B2: 进步最大（自动） | C2: 讲题最佳（手选） | D2: 帮扶最多（手选） | E2: 本期主动画（自动） | F2: 漫画主题 | G2: 是否已生成 | H2: 备注 | J2: 姓名 | K2: 本周分 | L2: 上周分 | M2: 进步
A3: 第1周 | E3: =IF(AND(B3="",C3="",D3=""),"",IFERROR(IF(AND(VLOOKUP(B3,学生档案!$C:$J,8,FALSE)<>"",OR(VLOOKUP(B3,学生档案!$C:$J,8,FALSE)=VLOOKUP(C3,学生档案!$C:$J,8,FALSE),VLOOKUP(B3,学生档案!$C:$J,8,FALSE)=VLOOKUP(D3,学生档案!$C:$J,8,FALSE))),VLOOKUP(B3,学生档案!$C:$J,8,FALSE),IF(AND(C3<>"",D3<>"",VLOOKUP(C3,学生档案!$C:$J,8,FALSE)=VLOOKUP(D3,学生档案!$C:$J,8,FALSE)),VLOOKUP(C3,学生档案!$C:$J,8,FALSE),IFERROR(IF(VLOOKUP(B3,学生档案!$C:$J,8,FALSE)<>"",VLOOKUP(B3,学生档案!$C:$J,8,FALSE),VLOOKUP(B3,学生档案!$C:$I,7,FALSE)),""))),"")) | J3: =IF(每周积分!B3="","",每周积分!B3) | K3: =IF(J3="","",IFERROR(INDEX(每周积分!C3:T3,1,每周积分!$X$1),0)) | L3: =IF(OR(J3="",每周积分!$X$1<=1),"",IFERROR(INDEX(每周积分!C3:T3,1,每周积分!$X$1-1),0)) | M3: =IF(J3="","",IF(每周积分!$X$1<=1,"",N(K3)-N(L3)))
A4: 第2周 | B4: =IF(每周积分!$X$1<>2,"",IFERROR(INDEX($J$3:$J$52,MATCH(MAX($M$3:$M$52),$M$3:$M$52,0)),"")) | E4: =IF(AND(B4="",C4="",D4=""),"",IFERROR(IF(AND(VLOOKUP(B4,学生档案!$C:$J,8,FALSE)<>"",OR(VLOOKUP(B4,学生档案!$C:$J,8,FALSE)=VLOOKUP(C4,学生档案!$C:$J,8,FALSE),VLOOKUP(B4,学生档案!$C:$J,8,FALSE)=VLOOKUP(D4,学生档案!$C:$J,8,FALSE))),VLOOKUP(B4,学生档案!$C:$J,8,FALSE),IF(AND(C4<>"",D4<>"",VLOOKUP(C4,学生档案!$C:$J,8,FALSE)=VLOOKUP(D4,学生档案!$C:$J,8,FALSE)),VLOOKUP(C4,学生档案!$C:$J,8,FALSE),IFERROR(IF(VLOOKUP(B4,学生档案!$C:$J,8,FALSE)<>"",VLOOKUP(B4,学生档案!$C:$J,8,FALSE),VLOOKUP(B4,学生档案!$C:$I,7,FALSE)),""))),"")) | J4: =IF(每周积分!B4="","",每周积分!B4) | K4: =IF(J4="","",IFERROR(INDEX(每周积分!C4:T4,1,每周积分!$X$1),0)) | L4: =IF(OR(J4="",每周积分!$X$1<=1),"",IFERROR(INDEX(每周积分!C4:T4,1,每周积分!$X$1-1),0)) | M4: =IF(J4="","",IF(每周积分!$X$1<=1,"",N(K4)-N(L4)))
A5: 第3周 | B5: =IF(每周积分!$X$1<>3,"",IFERROR(INDEX($J$3:$J$52,MATCH(MAX($M$3:$M$52),$M$3:$M$52,0)),"")) | E5: =IF(AND(B5="",C5="",D5=""),"",IFERROR(IF(AND(VLOOKUP(B5,学生档案!$C:$J,8,FALSE)<>"",OR(VLOOKUP(B5,学生档案!$C:$J,8,FALSE)=VLOOKUP(C5,学生档案!$C:$J,8,FALSE),VLOOKUP(B5,学生档案!$C:$J,8,FALSE)=VLOOKUP(D5,学生档案!$C:$J,8,FALSE))),VLOOKUP(B5,学生档案!$C:$J,8,FALSE),IF(AND(C5<>"",D5<>"",VLOOKUP(C5,学生档案!$C:$J,8,FALSE)=VLOOKUP(D5,学生档案!$C:$J,8,FALSE)),VLOOKUP(C5,学生档案!$C:$J,8,FALSE),IFERROR(IF(VLOOKUP(B5,学生档案!$C:$J,8,FALSE)<>"",VLOOKUP(B5,学生档案!$C:$J,8,FALSE),VLOOKUP(B5,学生档案!$C:$I,7,FALSE)),""))),"")) | J5: =IF(每周积分!B5="","",每周积分!B5) | K5: =IF(J5="","",IFERROR(INDEX(每周积分!C5:T5,1,每周积分!$X$1),0)) | L5: =IF(OR(J5="",每周积分!$X$1<=1),"",IFERROR(INDEX(每周积分!C5:T5,1,每周积分!$X$1-1),0)) | M5: =IF(J5="","",IF(每周积分!$X$1<=1,"",N(K5)-N(L5)))
A6: 第4周 | B6: =IF(每周积分!$X$1<>4,"",IFERROR(INDEX($J$3:$J$52,MATCH(MAX($M$3:$M$52),$M$3:$M$52,0)),"")) | E6: =IF(AND(B6="",C6="",D6=""),"",IFERROR(IF(AND(VLOOKUP(B6,学生档案!$C:$J,8,FALSE)<>"",OR(VLOOKUP(B6,学生档案!$C:$J,8,FALSE)=VLOOKUP(C6,学生档案!$C:$J,8,FALSE),VLOOKUP(B6,学生档案!$C:$J,8,FALSE)=VLOOKUP(D6,学生档案!$C:$J,8,FALSE))),VLOOKUP(B6,学生档案!$C:$J,8,FALSE),IF(AND(C6<>"",D6<>"",VLOOKUP(C6,学生档案!$C:$J,8,FALSE)=VLOOKUP(D6,学生档案!$C:$J,8,FALSE)),VLOOKUP(C6,学生档案!$C:$J,8,FALSE),IFERROR(IF(VLOOKUP(B6,学生档案!$C:$J,8,FALSE)<>"",VLOOKUP(B6,学生档案!$C:$J,8,FALSE),VLOOKUP(B6,学生档案!$C:$I,7,FALSE)),""))),"")) | J6: =IF(每周积分!B6="","",每周积分!B6) | K6: =IF(J6="","",IFERROR(INDEX(每周积分!C6:T6,1,每周积分!$X$1),0)) | L6: =IF(OR(J6="",每周积分!$X$1<=1),"",IFERROR(INDEX(每周积分!C6:T6,1,每周积分!$X$1-1),0)) | M6: =IF(J6="","",IF(每周积分!$X$1<=1,"",N(K6)-N(L6)))
A7: 第5周 | B7: =IF(每周积分!$X$1<>5,"",IFERROR(INDEX($J$3:$J$52,MATCH(MAX($M$3:$M$52),$M$3:$M$52,0)),"")) | E7: =IF(AND(B7="",C7="",D7=""),"",IFERROR(IF(AND(VLOOKUP(B7,学生档案!$C:$J,8,FALSE)<>"",OR(VLOOKUP(B7,学生档案!$C:$J,8,FALSE)=VLOOKUP(C7,学生档案!$C:$J,8,FALSE),VLOOKUP(B7,学生档案!$C:$J,8,FALSE)=VLOOKUP(D7,学生档案!$C:$J,8,FALSE))),VLOOKUP(B7,学生档案!$C:$J,8,FALSE),IF(AND(C7<>"",D7<>"",VLOOKUP(C7,学生档案!$C:$J,8,FALSE)=VLOOKUP(D7,学生档案!$C:$J,8,FALSE)),VLOOKUP(C7,学生档案!$C:$J,8,FALSE),IFERROR(IF(VLOOKUP(B7,学生档案!$C:$J,8,FALSE)<>"",VLOOKUP(B7,学生档案!$C:$J,8,FALSE),VLOOKUP(B7,学生档案!$C:$I,7,FALSE)),""))),"")) | J7: =IF(每周积分!B7="","",每周积分!B7) | K7: =IF(J7="","",IFERROR(INDEX(每周积分!C7:T7,1,每周积分!$X$1),0)) | L7: =IF(OR(J7="",每周积分!$X$1<=1),"",IFERROR(INDEX(每周积分!C7:T7,1,每周积分!$X$1-1),0)) | M7: =IF(J7="","",IF(每周积分!$X$1<=1,"",N(K7)-N(L7)))
A8: 第6周 | B8: =IF(每周积分!$X$1<>6,"",IFERROR(INDEX($J$3:$J$52,MATCH(MAX($M$3:$M$52),$M$3:$M$52,0)),"")) | E8: =IF(AND(B8="",C8="",D8=""),"",IFERROR(IF(AND(VLOOKUP(B8,学生档案!$C:$J,8,FALSE)<>"",OR(VLOOKUP(B8,学生档案!$C:$J,8,FALSE)=VLOOKUP(C8,学生档案!$C:$J,8,FALSE),VLOOKUP(B8,学生档案!$C:$J,8,FALSE)=VLOOKUP(D8,学生档案!$C:$J,8,FALSE))),VLOOKUP(B8,学生档案!$C:$J,8,FALSE),IF(AND(C8<>"",D8<>"",VLOOKUP(C8,学生档案!$C:$J,8,FALSE)=VLOOKUP(D8,学生档案!$C:$J,8,FALSE)),VLOOKUP(C8,学生档案!$C:$J,8,FALSE),IFERROR(IF(VLOOKUP(B8,学生档案!$C:$J,8,FALSE)<>"",VLOOKUP(B8,学生档案!$C:$J,8,FALSE),VLOOKUP(B8,学生档案!$C:$I,7,FALSE)),""))),"")) | J8: =IF(每周积分!B8="","",每周积分!B8) | K8: =IF(J8="","",IFERROR(INDEX(每周积分!C8:T8,1,每周积分!$X$1),0)) | L8: =IF(OR(J8="",每周积分!$X$1<=1),"",IFERROR(INDEX(每周积分!C8:T8,1,每周积分!$X$1-1),0)) | M8: =IF(J8="","",IF(每周积分!$X$1<=1,"",N(K8)-N(L8)))
A9: 第7周 | B9: =IF(每周积分!$X$1<>7,"",IFERROR(INDEX($J$3:$J$52,MATCH(MAX($M$3:$M$52),$M$3:$M$52,0)),"")) | E9: =IF(AND(B9="",C9="",D9=""),"",IFERROR(IF(AND(VLOOKUP(B9,学生档案!$C:$J,8,FALSE)<>"",OR(VLOOKUP(B9,学生档案!$C:$J,8,FALSE)=VLOOKUP(C9,学生档案!$C:$J,8,FALSE),VLOOKUP(B9,学生档案!$C:$J,8,FALSE)=VLOOKUP(D9,学生档案!$C:$J,8,FALSE))),VLOOKUP(B9,学生档案!$C:$J,8,FALSE),IF(AND(C9<>"",D9<>"",VLOOKUP(C9,学生档案!$C:$J,8,FALSE)=VLOOKUP(D9,学生档案!$C:$J,8,FALSE)),VLOOKUP(C9,学生档案!$C:$J,8,FALSE),IFERROR(IF(VLOOKUP(B9,学生档案!$C:$J,8,FALSE)<>"",VLOOKUP(B9,学生档案!$C:$J,8,FALSE),VLOOKUP(B9,学生档案!$C:$I,7,FALSE)),""))),"")) | J9: =IF(每周积分!B9="","",每周积分!B9) | K9: =IF(J9="","",IFERROR(INDEX(每周积分!C9:T9,1,每周积分!$X$1),0)) | L9: =IF(OR(J9="",每周积分!$X$1<=1),"",IFERROR(INDEX(每周积分!C9:T9,1,每周积分!$X$1-1),0)) | M9: =IF(J9="","",IF(每周积分!$X$1<=1,"",N(K9)-N(L9)))
A10: 第8周 | B10: =IF(每周积分!$X$1<>8,"",IFERROR(INDEX($J$3:$J$52,MATCH(MAX($M$3:$M$52),$M$3:$M$52,0)),"")) | E10: =IF(AND(B10="",C10="",D10=""),"",IFERROR(IF(AND(VLOOKUP(B10,学生档案!$C:$J,8,FALSE)<>"",OR(VLOOKUP(B10,学生档案!$C:$J,8,FALSE)=VLOOKUP(C10,学生档案!$C:$J,8,FALSE),VLOOKUP(B10,学生档案!$C:$J,8,FALSE)=VLOOKUP(D10,学生档案!$C:$J,8,FALSE))),VLOOKUP(B10,学生档案!$C:$J,8,FALSE),IF(AND(C10<>"",D10<>"",VLOOKUP(C10,学生档案!$C:$J,8,FALSE)=VLOOKUP(D10,学生档案!$C:$J,8,FALSE)),VLOOKUP(C10,学生档案!$C:$J,8,FALSE),IFERROR(IF(VLOOKUP(B10,学生档案!$C:$J,8,FALSE)<>"",VLOOKUP(B10,学生档案!$C:$J,8,FALSE),VLOOKUP(B10,学生档案!$C:$I,7,FALSE)),""))),"")) | J10: =IF(每周积分!B10="","",每周积分!B10) | K10: =IF(J10="","",IFERROR(INDEX(每周积分!C10:T10,1,每周积分!$X$1),0)) | L10: =IF(OR(J10="",每周积分!$X$1<=1),"",IFERROR(INDEX(每周积分!C10:T10,1,每周积分!$X$1-1),0)) | M10: =IF(J10="","",IF(每周积分!$X$1<=1,"",N(K10)-N(L10)))
A11: 第9周 | B11: =IF(每周积分!$X$1<>9,"",IFERROR(INDEX($J$3:$J$52,MATCH(MAX($M$3:$M$52),$M$3:$M$52,0)),"")) | E11: =IF(AND(B11="",C11="",D11=""),"",IFERROR(IF(AND(VLOOKUP(B11,学生档案!$C:$J,8,FALSE)<>"",OR(VLOOKUP(B11,学生档案!$C:$J,8,FALSE)=VLOOKUP(C11,学生档案!$C:$J,8,FALSE),VLOOKUP(B11,学生档案!$C:$J,8,FALSE)=VLOOKUP(D11,学生档案!$C:$J,8,FALSE))),VLOOKUP(B11,学生档案!$C:$J,8,FALSE),IF(AND(C11<>"",D11<>"",VLOOKUP(C11,学生档案!$C:$J,8,FALSE)=VLOOKUP(D11,学生档案!$C:$J,8,FALSE)),VLOOKUP(C11,学生档案!$C:$J,8,FALSE),IFERROR(IF(VLOOKUP(B11,学生档案!$C:$J,8,FALSE)<>"",VLOOKUP(B11,学生档案!$C:$J,8,FALSE),VLOOKUP(B11,学生档案!$C:$I,7,FALSE)),""))),"")) | J11: =IF(每周积分!B11="","",每周积分!B11) | K11: =IF(J11="","",IFERROR(INDEX(每周积分!C11:T11,1,每周积分!$X$1),0)) | L11: =IF(OR(J11="",每周积分!$X$1<=1),"",IFERROR(INDEX(每周积分!C11:T11,1,每周积分!$X$1-1),0)) | M11: =IF(J11="","",IF(每周积分!$X$1<=1,"",N(K11)-N(L11)))
A12: 第10周 | B12: =IF(每周积分!$X$1<>10,"",IFERROR(INDEX($J$3:$J$52,MATCH(MAX($M$3:$M$52),$M$3:$M$52,0)),"")) | E12: =IF(AND(B12="",C12="",D12=""),"",IFERROR(IF(AND(VLOOKUP(B12,学生档案!$C:$J,8,FALSE)<>"",OR(VLOOKUP(B12,学生档案!$C:$J,8,FALSE)=VLOOKUP(C12,学生档案!$C:$J,8,FALSE),VLOOKUP(B12,学生档案!$C:$J,8,FALSE)=VLOOKUP(D12,学生档案!$C:$J,8,FALSE))),VLOOKUP(B12,学生档案!$C:$J,8,FALSE),IF(AND(C12<>"",D12<>"",VLOOKUP(C12,学生档案!$C:$J,8,FALSE)=VLOOKUP(D12,学生档案!$C:$J,8,FALSE)),VLOOKUP(C12,学生档案!$C:$J,8,FALSE),IFERROR(IF(VLOOKUP(B12,学生档案!$C:$J,8,FALSE)<>"",VLOOKUP(B12,学生档案!$C:$J,8,FALSE),VLOOKUP(B12,学生档案!$C:$I,7,FALSE)),""))),"")) | J12: =IF(每周积分!B12="","",每周积分!B12) | K12: =IF(J12="","",IFERROR(INDEX(每周积分!C12:T12,1,每周积分!$X$1),0)) | L12: =IF(OR(J12="",每周积分!$X$1<=1),"",IFERROR(INDEX(每周积分!C12:T12,1,每周积分!$X$1-1),0)) | M12: =IF(J12="","",IF(每周积分!$X$1<=1,"",N(K12)-N(L12)))
A13: 第11周 | B13: =IF(每周积分!$X$1<>11,"",IFERROR(INDEX($J$3:$J$52,MATCH(MAX($M$3:$M$52),$M$3:$M$52,0)),"")) | E13: =IF(AND(B13="",C13="",D13=""),"",IFERROR(IF(AND(VLOOKUP(B13,学生档案!$C:$J,8,FALSE)<>"",OR(VLOOKUP(B13,学生档案!$C:$J,8,FALSE)=VLOOKUP(C13,学生档案!$C:$J,8,FALSE),VLOOKUP(B13,学生档案!$C:$J,8,FALSE)=VLOOKUP(D13,学生档案!$C:$J,8,FALSE))),VLOOKUP(B13,学生档案!$C:$J,8,FALSE),IF(AND(C13<>"",D13<>"",VLOOKUP(C13,学生档案!$C:$J,8,FALSE)=VLOOKUP(D13,学生档案!$C:$J,8,FALSE)),VLOOKUP(C13,学生档案!$C:$J,8,FALSE),IFERROR(IF(VLOOKUP(B13,学生档案!$C:$J,8,FALSE)<>"",VLOOKUP(B13,学生档案!$C:$J,8,FALSE),VLOOKUP(B13,学生档案!$C:$I,7,FALSE)),""))),"")) | J13: =IF(每周积分!B13="","",每周积分!B13) | K13: =IF(J13="","",IFERROR(INDEX(每周积分!C13:T13,1,每周积分!$X$1),0)) | L13: =IF(OR(J13="",每周积分!$X$1<=1),"",IFERROR(INDEX(每周积分!C13:T13,1,每周积分!$X$1-1),0)) | M13: =IF(J13="","",IF(每周积分!$X$1<=1,"",N(K13)-N(L13)))
A14: 第12周 | B14: =IF(每周积分!$X$1<>12,"",IFERROR(INDEX($J$3:$J$52,MATCH(MAX($M$3:$M$52),$M$3:$M$52,0)),"")) | E14: =IF(AND(B14="",C14="",D14=""),"",IFERROR(IF(AND(VLOOKUP(B14,学生档案!$C:$J,8,FALSE)<>"",OR(VLOOKUP(B14,学生档案!$C:$J,8,FALSE)=VLOOKUP(C14,学生档案!$C:$J,8,FALSE),VLOOKUP(B14,学生档案!$C:$J,8,FALSE)=VLOOKUP(D14,学生档案!$C:$J,8,FALSE))),VLOOKUP(B14,学生档案!$C:$J,8,FALSE),IF(AND(C14<>"",D14<>"",VLOOKUP(C14,学生档案!$C:$J,8,FALSE)=VLOOKUP(D14,学生档案!$C:$J,8,FALSE)),VLOOKUP(C14,学生档案!$C:$J,8,FALSE),IFERROR(IF(VLOOKUP(B14,学生档案!$C:$J,8,FALSE)<>"",VLOOKUP(B14,学生档案!$C:$J,8,FALSE),VLOOKUP(B14,学生档案!$C:$I,7,FALSE)),""))),"")) | J14: =IF(每周积分!B14="","",每周积分!B14) | K14: =IF(J14="","",IFERROR(INDEX(每周积分!C14:T14,1,每周积分!$X$1),0)) | L14: =IF(OR(J14="",每周积分!$X$1<=1),"",IFERROR(INDEX(每周积分!C14:T14,1,每周积分!$X$1-1),0)) | M14: =IF(J14="","",IF(每周积分!$X$1<=1,"",N(K14)-N(L14)))
A15: 第13周 | B15: =IF(每周积分!$X$1<>13,"",IFERROR(INDEX($J$3:$J$52,MATCH(MAX($M$3:$M$52),$M$3:$M$52,0)),"")) | E15: =IF(AND(B15="",C15="",D15=""),"",IFERROR(IF(AND(VLOOKUP(B15,学生档案!$C:$J,8,FALSE)<>"",OR(VLOOKUP(B15,学生档案!$C:$J,8,FALSE)=VLOOKUP(C15,学生档案!$C:$J,8,FALSE),VLOOKUP(B15,学生档案!$C:$J,8,FALSE)=VLOOKUP(D15,学生档案!$C:$J,8,FALSE))),VLOOKUP(B15,学生档案!$C:$J,8,FALSE),IF(AND(C15<>"",D15<>"",VLOOKUP(C15,学生档案!$C:$J,8,FALSE)=VLOOKUP(D15,学生档案!$C:$J,8,FALSE)),VLOOKUP(C15,学生档案!$C:$J,8,FALSE),IFERROR(IF(VLOOKUP(B15,学生档案!$C:$J,8,FALSE)<>"",VLOOKUP(B15,学生档案!$C:$J,8,FALSE),VLOOKUP(B15,学生档案!$C:$I,7,FALSE)),""))),"")) | J15: =IF(每周积分!B15="","",每周积分!B15) | K15: =IF(J15="","",IFERROR(INDEX(每周积分!C15:T15,1,每周积分!$X$1),0)) | L15: =IF(OR(J15="",每周积分!$X$1<=1),"",IFERROR(INDEX(每周积分!C15:T15,1,每周积分!$X$1-1),0)) | M15: =IF(J15="","",IF(每周积分!$X$1<=1,"",N(K15)-N(L15)))
A16: 第14周 | B16: =IF(每周积分!$X$1<>14,"",IFERROR(INDEX($J$3:$J$52,MATCH(MAX($M$3:$M$52),$M$3:$M$52,0)),"")) | E16: =IF(AND(B16="",C16="",D16=""),"",IFERROR(IF(AND(VLOOKUP(B16,学生档案!$C:$J,8,FALSE)<>"",OR(VLOOKUP(B16,学生档案!$C:$J,8,FALSE)=VLOOKUP(C16,学生档案!$C:$J,8,FALSE),VLOOKUP(B16,学生档案!$C:$J,8,FALSE)=VLOOKUP(D16,学生档案!$C:$J,8,FALSE))),VLOOKUP(B16,学生档案!$C:$J,8,FALSE),IF(AND(C16<>"",D16<>"",VLOOKUP(C16,学生档案!$C:$J,8,FALSE)=VLOOKUP(D16,学生档案!$C:$J,8,FALSE)),VLOOKUP(C16,学生档案!$C:$J,8,FALSE),IFERROR(IF(VLOOKUP(B16,学生档案!$C:$J,8,FALSE)<>"",VLOOKUP(B16,学生档案!$C:$J,8,FALSE),VLOOKUP(B16,学生档案!$C:$I,7,FALSE)),""))),"")) | J16: =IF(每周积分!B16="","",每周积分!B16) | K16: =IF(J16="","",IFERROR(INDEX(每周积分!C16:T16,1,每周积分!$X$1),0)) | L16: =IF(OR(J16="",每周积分!$X$1<=1),"",IFERROR(INDEX(每周积分!C16:T16,1,每周积分!$X$1-1),0)) | M16: =IF(J16="","",IF(每周积分!$X$1<=1,"",N(K16)-N(L16)))
A17: 第15周 | B17: =IF(每周积分!$X$1<>15,"",IFERROR(INDEX($J$3:$J$52,MATCH(MAX($M$3:$M$52),$M$3:$M$52,0)),"")) | E17: =IF(AND(B17="",C17="",D17=""),"",IFERROR(IF(AND(VLOOKUP(B17,学生档案!$C:$J,8,FALSE)<>"",OR(VLOOKUP(B17,学生档案!$C:$J,8,FALSE)=VLOOKUP(C17,学生档案!$C:$J,8,FALSE),VLOOKUP(B17,学生档案!$C:$J,8,FALSE)=VLOOKUP(D17,学生档案!$C:$J,8,FALSE))),VLOOKUP(B17,学生档案!$C:$J,8,FALSE),IF(AND(C17<>"",D17<>"",VLOOKUP(C17,学生档案!$C:$J,8,FALSE)=VLOOKUP(D17,学生档案!$C:$J,8,FALSE)),VLOOKUP(C17,学生档案!$C:$J,8,FALSE),IFERROR(IF(VLOOKUP(B17,学生档案!$C:$J,8,FALSE)<>"",VLOOKUP(B17,学生档案!$C:$J,8,FALSE),VLOOKUP(B17,学生档案!$C:$I,7,FALSE)),""))),"")) | J17: =IF(每周积分!B17="","",每周积分!B17) | K17: =IF(J17="","",IFERROR(INDEX(每周积分!C17:T17,1,每周积分!$X$1),0)) | L17: =IF(OR(J17="",每周积分!$X$1<=1),"",IFERROR(INDEX(每周积分!C17:T17,1,每周积分!$X$1-1),0)) | M17: =IF(J17="","",IF(每周积分!$X$1<=1,"",N(K17)-N(L17)))
A18: 第16周 | B18: =IF(每周积分!$X$1<>16,"",IFERROR(INDEX($J$3:$J$52,MATCH(MAX($M$3:$M$52),$M$3:$M$52,0)),"")) | E18: =IF(AND(B18="",C18="",D18=""),"",IFERROR(IF(AND(VLOOKUP(B18,学生档案!$C:$J,8,FALSE)<>"",OR(VLOOKUP(B18,学生档案!$C:$J,8,FALSE)=VLOOKUP(C18,学生档案!$C:$J,8,FALSE),VLOOKUP(B18,学生档案!$C:$J,8,FALSE)=VLOOKUP(D18,学生档案!$C:$J,8,FALSE))),VLOOKUP(B18,学生档案!$C:$J,8,FALSE),IF(AND(C18<>"",D18<>"",VLOOKUP(C18,学生档案!$C:$J,8,FALSE)=VLOOKUP(D18,学生档案!$C:$J,8,FALSE)),VLOOKUP(C18,学生档案!$C:$J,8,FALSE),IFERROR(IF(VLOOKUP(B18,学生档案!$C:$J,8,FALSE)<>"",VLOOKUP(B18,学生档案!$C:$J,8,FALSE),VLOOKUP(B18,学生档案!$C:$I,7,FALSE)),""))),"")) | J18: =IF(每周积分!B18="","",每周积分!B18) | K18: =IF(J18="","",IFERROR(INDEX(每周积分!C18:T18,1,每周积分!$X$1),0)) | L18: =IF(OR(J18="",每周积分!$X$1<=1),"",IFERROR(INDEX(每周积分!C18:T18,1,每周积分!$X$1-1),0)) | M18: =IF(J18="","",IF(每周积分!$X$1<=1,"",N(K18)-N(L18)))
A19: 第17周 | B19: =IF(每周积分!$X$1<>17,"",IFERROR(INDEX($J$3:$J$52,MATCH(MAX($M$3:$M$52),$M$3:$M$52,0)),"")) | E19: =IF(AND(B19="",C19="",D19=""),"",IFERROR(IF(AND(VLOOKUP(B19,学生档案!$C:$J,8,FALSE)<>"",OR(VLOOKUP(B19,学生档案!$C:$J,8,FALSE)=VLOOKUP(C19,学生档案!$C:$J,8,FALSE),VLOOKUP(B19,学生档案!$C:$J,8,FALSE)=VLOOKUP(D19,学生档案!$C:$J,8,FALSE))),VLOOKUP(B19,学生档案!$C:$J,8,FALSE),IF(AND(C19<>"",D19<>"",VLOOKUP(C19,学生档案!$C:$J,8,FALSE)=VLOOKUP(D19,学生档案!$C:$J,8,FALSE)),VLOOKUP(C19,学生档案!$C:$J,8,FALSE),IFERROR(IF(VLOOKUP(B19,学生档案!$C:$J,8,FALSE)<>"",VLOOKUP(B19,学生档案!$C:$J,8,FALSE),VLOOKUP(B19,学生档案!$C:$I,7,FALSE)),""))),"")) | J19: =IF(每周积分!B19="","",每周积分!B19) | K19: =IF(J19="","",IFERROR(INDEX(每周积分!C19:T19,1,每周积分!$X$1),0)) | L19: =IF(OR(J19="",每周积分!$X$1<=1),"",IFERROR(INDEX(每周积分!C19:T19,1,每周积分!$X$1-1),0)) | M19: =IF(J19="","",IF(每周积分!$X$1<=1,"",N(K19)-N(L19)))
A20: 第18周 | B20: =IF(每周积分!$X$1<>18,"",IFERROR(INDEX($J$3:$J$52,MATCH(MAX($M$3:$M$52),$M$3:$M$52,0)),"")) | E20: =IF(AND(B20="",C20="",D20=""),"",IFERROR(IF(AND(VLOOKUP(B20,学生档案!$C:$J,8,FALSE)<>"",OR(VLOOKUP(B20,学生档案!$C:$J,8,FALSE)=VLOOKUP(C20,学生档案!$C:$J,8,FALSE),VLOOKUP(B20,学生档案!$C:$J,8,FALSE)=VLOOKUP(D20,学生档案!$C:$J,8,FALSE))),VLOOKUP(B20,学生档案!$C:$J,8,FALSE),IF(AND(C20<>"",D20<>"",VLOOKUP(C20,学生档案!$C:$J,8,FALSE)=VLOOKUP(D20,学生档案!$C:$J,8,FALSE)),VLOOKUP(C20,学生档案!$C:$J,8,FALSE),IFERROR(IF(VLOOKUP(B20,学生档案!$C:$J,8,FALSE)<>"",VLOOKUP(B20,学生档案!$C:$J,8,FALSE),VLOOKUP(B20,学生档案!$C:$I,7,FALSE)),""))),"")) | J20: =IF(每周积分!B20="","",每周积分!B20) | K20: =IF(J20="","",IFERROR(INDEX(每周积分!C20:T20,1,每周积分!$X$1),0)) | L20: =IF(OR(J20="",每周积分!$X$1<=1),"",IFERROR(INDEX(每周积分!C20:T20,1,每周积分!$X$1-1),0)) | M20: =IF(J20="","",IF(每周积分!$X$1<=1,"",N(K20)-N(L20)))
J21: =IF(每周积分!B21="","",每周积分!B21) | K21: =IF(J21="","",IFERROR(INDEX(每周积分!C21:T21,1,每周积分!$X$1),0)) | L21: =IF(OR(J21="",每周积分!$X$1<=1),"",IFERROR(INDEX(每周积分!C21:T21,1,每周积分!$X$1-1),0)) | M21: =IF(J21="","",IF(每周积分!$X$1<=1,"",N(K21)-N(L21)))
J22: =IF(每周积分!B22="","",每周积分!B22) | K22: =IF(J22="","",IFERROR(INDEX(每周积分!C22:T22,1,每周积分!$X$1),0)) | L22: =IF(OR(J22="",每周积分!$X$1<=1),"",IFERROR(INDEX(每周积分!C22:T22,1,每周积分!$X$1-1),0)) | M22: =IF(J22="","",IF(每周积分!$X$1<=1,"",N(K22)-N(L22)))
J23: =IF(每周积分!B23="","",每周积分!B23) | K23: =IF(J23="","",IFERROR(INDEX(每周积分!C23:T23,1,每周积分!$X$1),0)) | L23: =IF(OR(J23="",每周积分!$X$1<=1),"",IFERROR(INDEX(每周积分!C23:T23,1,每周积分!$X$1-1),0)) | M23: =IF(J23="","",IF(每周积分!$X$1<=1,"",N(K23)-N(L23)))
J24: =IF(每周积分!B24="","",每周积分!B24) | K24: =IF(J24="","",IFERROR(INDEX(每周积分!C24:T24,1,每周积分!$X$1),0)) | L24: =IF(OR(J24="",每周积分!$X$1<=1),"",IFERROR(INDEX(每周积分!C24:T24,1,每周积分!$X$1-1),0)) | M24: =IF(J24="","",IF(每周积分!$X$1<=1,"",N(K24)-N(L24)))
J25: =IF(每周积分!B25="","",每周积分!B25) | K25: =IF(J25="","",IFERROR(INDEX(每周积分!C25:T25,1,每周积分!$X$1),0)) | L25: =IF(OR(J25="",每周积分!$X$1<=1),"",IFERROR(INDEX(每周积分!C25:T25,1,每周积分!$X$1-1),0)) | M25: =IF(J25="","",IF(每周积分!$X$1<=1,"",N(K25)-N(L25)))
J26: =IF(每周积分!B26="","",每周积分!B26) | K26: =IF(J26="","",IFERROR(INDEX(每周积分!C26:T26,1,每周积分!$X$1),0)) | L26: =IF(OR(J26="",每周积分!$X$1<=1),"",IFERROR(INDEX(每周积分!C26:T26,1,每周积分!$X$1-1),0)) | M26: =IF(J26="","",IF(每周积分!$X$1<=1,"",N(K26)-N(L26)))
J27: =IF(每周积分!B27="","",每周积分!B27) | K27: =IF(J27="","",IFERROR(INDEX(每周积分!C27:T27,1,每周积分!$X$1),0)) | L27: =IF(OR(J27="",每周积分!$X$1<=1),"",IFERROR(INDEX(每周积分!C27:T27,1,每周积分!$X$1-1),0)) | M27: =IF(J27="","",IF(每周积分!$X$1<=1,"",N(K27)-N(L27)))
J28: =IF(每周积分!B28="","",每周积分!B28) | K28: =IF(J28="","",IFERROR(INDEX(每周积分!C28:T28,1,每周积分!$X$1),0)) | L28: =IF(OR(J28="",每周积分!$X$1<=1),"",IFERROR(INDEX(每周积分!C28:T28,1,每周积分!$X$1-1),0)) | M28: =IF(J28="","",IF(每周积分!$X$1<=1,"",N(K28)-N(L28)))
J29: =IF(每周积分!B29="","",每周积分!B29) | K29: =IF(J29="","",IFERROR(INDEX(每周积分!C29:T29,1,每周积分!$X$1),0)) | L29: =IF(OR(J29="",每周积分!$X$1<=1),"",IFERROR(INDEX(每周积分!C29:T29,1,每周积分!$X$1-1),0)) | M29: =IF(J29="","",IF(每周积分!$X$1<=1,"",N(K29)-N(L29)))
J30: =IF(每周积分!B30="","",每周积分!B30) | K30: =IF(J30="","",IFERROR(INDEX(每周积分!C30:T30,1,每周积分!$X$1),0)) | L30: =IF(OR(J30="",每周积分!$X$1<=1),"",IFERROR(INDEX(每周积分!C30:T30,1,每周积分!$X$1-1),0)) | M30: =IF(J30="","",IF(每周积分!$X$1<=1,"",N(K30)-N(L30)))
J31: =IF(每周积分!B31="","",每周积分!B31) | K31: =IF(J31="","",IFERROR(INDEX(每周积分!C31:T31,1,每周积分!$X$1),0)) | L31: =IF(OR(J31="",每周积分!$X$1<=1),"",IFERROR(INDEX(每周积分!C31:T31,1,每周积分!$X$1-1),0)) | M31: =IF(J31="","",IF(每周积分!$X$1<=1,"",N(K31)-N(L31)))
J32: =IF(每周积分!B32="","",每周积分!B32) | K32: =IF(J32="","",IFERROR(INDEX(每周积分!C32:T32,1,每周积分!$X$1),0)) | L32: =IF(OR(J32="",每周积分!$X$1<=1),"",IFERROR(INDEX(每周积分!C32:T32,1,每周积分!$X$1-1),0)) | M32: =IF(J32="","",IF(每周积分!$X$1<=1,"",N(K32)-N(L32)))
... J52: =IF(每周积分!B52="","",每周积分!B52) | K52: =IF(J52="","",IFERROR(INDEX(每周积分!C52:T52,1,每周积分!$X$1),0)) | L52: =IF(OR(J52="",每周积分!$X$1<=1),"",IFERROR(INDEX(每周积分!C52:T52,1,每周积分!$X$1-1),0)) | M52: =IF(J52="","",IF(每周积分!$X$1<=1,"",N(K52)-N(L52)))

Sheet 问卷统计
A1: 公式自动数。收齐后看第5/18/19/20题。
A2: 统计项 | B2: 选项 | C2: 人数 | D2: 占比 | E2: 用途 | F2: 列
A3: 1 以前接触过会计吗 | B3: 完全没有 | C3: =COUNTIF(学生档案!$E$3:$E$52,B3) | D3: =IF(COUNTA(学生档案!$C$3:$C$52)=0,"",C3/COUNTA(学生档案!$C$3:$C$52)) | E3: 分组：每组放一个完全没有的 | F3: E
B4: 听说过没学过 | C4: =COUNTIF(学生档案!$E$3:$E$52,B4) | D4: =IF(COUNTA(学生档案!$C$3:$C$52)=0,"",C4/COUNTA(学生档案!$C$3:$C$52)) | E4: 分组：每组放一个完全没有的 | F4: E
B5: 家里有人做会计 | C5: =COUNTIF(学生档案!$E$3:$E$52,B5) | D5: =IF(COUNTA(学生档案!$C$3:$C$52)=0,"",C5/COUNTA(学生档案!$C$3:$C$52)) | E5: 分组：每组放一个完全没有的 | F5: E
B6: 自己学过一点 | C6: =COUNTIF(学生档案!$E$3:$E$52,B6) | D6: =IF(COUNTA(学生档案!$C$3:$C$52)=0,"",C6/COUNTA(学生档案!$C$3:$C$52)) | E6: 分组：每组放一个完全没有的 | F6: E
A7: 2 数学怎么样 | B7: 还不错 | C7: =COUNTIF(学生档案!$F$3:$F$52,B7) | D7: =IF(COUNTA(学生档案!$C$3:$C$52)=0,"",C7/COUNTA(学生档案!$C$3:$C$52)) | E7: 分组：每组放一个还不错的 | F7: F
B8: 一般 | C8: =COUNTIF(学生档案!$F$3:$F$52,B8) | D8: =IF(COUNTA(学生档案!$C$3:$C$52)=0,"",C8/COUNTA(学生档案!$C$3:$C$52)) | E8: 分组：每组放一个还不错的 | F8: F
B9: 比较吃力 | C9: =COUNTIF(学生档案!$F$3:$F$52,B9) | D9: =IF(COUNTA(学生档案!$C$3:$C$52)=0,"",C9/COUNTA(学生档案!$C$3:$C$52)) | E9: 分组：每组放一个还不错的 | F9: F
B10: 看到数字就头大 | C10: =COUNTIF(学生档案!$F$3:$F$52,B10) | D10: =IF(COUNTA(学生档案!$C$3:$C$52)=0,"",C10/COUNTA(学生档案!$C$3:$C$52)) | E10: 分组：每组放一个还不错的 | F10: F
A11: 3 希望怎么上课 | B11: 多做游戏比赛 | C11: =COUNTIF(学生档案!$G$3:$G$52,"*"&B11&"*") | D11: =IF(COUNTA(学生档案!$C$3:$C$52)=0,"",C11/COUNTA(学生档案!$C$3:$C$52)) | E11: 游戏超70% → 网页工具给足时间 | F11: G
B12: 多讲实际案例 | C12: =COUNTIF(学生档案!$G$3:$G$52,"*"&B12&"*") | D12: =IF(COUNTA(学生档案!$C$3:$C$52)=0,"",C12/COUNTA(学生档案!$C$3:$C$52)) | E12: 游戏超70% → 网页工具给足时间 | F12: G
B13: 多动手实训 | C13: =COUNTIF(学生档案!$G$3:$G$52,"*"&B13&"*") | D13: =IF(COUNTA(学生档案!$C$3:$C$52)=0,"",C13/COUNTA(学生档案!$C$3:$C$52)) | E13: 游戏超70% → 网页工具给足时间 | F13: G
B14: 讲慢一点细一点 | C14: =COUNTIF(学生档案!$G$3:$G$52,"*"&B14&"*") | D14: =IF(COUNTA(学生档案!$C$3:$C$52)=0,"",C14/COUNTA(学生档案!$C$3:$C$52)) | E14: 游戏超70% → 网页工具给足时间 | F14: G
B15: 多用视频动画 | C15: =COUNTIF(学生档案!$G$3:$G$52,"*"&B15&"*") | D15: =IF(COUNTA(学生档案!$C$3:$C$52)=0,"",C15/COUNTA(学生档案!$C$3:$C$52)) | E15: 游戏超70% → 网页工具给足时间 | F15: G
B16: 多小组讨论 | C16: =COUNTIF(学生档案!$G$3:$G$52,"*"&B16&"*") | D16: =IF(COUNTA(学生档案!$C$3:$C$52)=0,"",C16/COUNTA(学生档案!$C$3:$C$52)) | E16: 游戏超70% → 网页工具给足时间 | F16: G
A17: 5 上课最想看到哪个动画 | B17: 蜡笔小新 | C17: =COUNTIF(学生档案!$I$3:$I$52,B17) | D17: =IF(COUNTA(学生档案!$C$3:$C$52)=0,"",C17/COUNTA(学生档案!$C$3:$C$52)) | E17: 最高票 = 班底动画 | F17: I
B18: 哆啦A梦 | C18: =COUNTIF(学生档案!$I$3:$I$52,B18) | D18: =IF(COUNTA(学生档案!$C$3:$C$52)=0,"",C18/COUNTA(学生档案!$C$3:$C$52)) | E18: 最高票 = 班底动画 | F18: I
B19: 喜羊羊与灰太狼 | C19: =COUNTIF(学生档案!$I$3:$I$52,B19) | D19: =IF(COUNTA(学生档案!$C$3:$C$52)=0,"",C19/COUNTA(学生档案!$C$3:$C$52)) | E19: 最高票 = 班底动画 | F19: I
A20: 16 想不想和喜欢的卡通同框 | B20: 想，和我喜欢的角色同框 | C20: =COUNTIF(学生档案!$T$3:$T$52,B20) | D20: =IF(COUNTA(学生档案!$C$3:$C$52)=0,"",C20/COUNTA(学生档案!$C$3:$C$52)) | E20: 出镜先找前两档 | F20: T
B21: 可以试试 | C21: =COUNTIF(学生档案!$T$3:$T$52,B21) | D21: =IF(COUNTA(学生档案!$C$3:$C$52)=0,"",C21/COUNTA(学生档案!$C$3:$C$52)) | E21: 出镜先找前两档 | F21: T
B22: 先看别人的，先别画我 | C22: =COUNTIF(学生档案!$T$3:$T$52,B22) | D22: =IF(COUNTA(学生档案!$C$3:$C$52)=0,"",C22/COUNTA(学生档案!$C$3:$C$52)) | E22: 出镜先找前两档 | F22: T
B23: 这次先不参加 | C23: =COUNTIF(学生档案!$T$3:$T$52,B23) | D23: =IF(COUNTA(学生档案!$C$3:$C$52)=0,"",C23/COUNTA(学生档案!$C$3:$C$52)) | E23: 出镜先找前两档 | F23: T
A24: 18 照片画卡通 | B24: 随便用 | C24: =COUNTIF(学生档案!$V$3:$V$52,B24) | D24: =IF(COUNTA(学生档案!$C$3:$C$52)=0,"",C24/COUNTA(学生档案!$C$3:$C$52)) | E24: 不要用 = 红线 | F24: V
B25: 可以但别画太丑 | C25: =COUNTIF(学生档案!$V$3:$V$52,B25) | D25: =IF(COUNTA(学生档案!$C$3:$C$52)=0,"",C25/COUNTA(学生档案!$C$3:$C$52)) | E25: 不要用 = 红线 | F25: V
B26: 只给我自己看 | C26: =COUNTIF(学生档案!$V$3:$V$52,B26) | D26: =IF(COUNTA(学生档案!$C$3:$C$52)=0,"",C26/COUNTA(学生档案!$C$3:$C$52)) | E26: 不要用 = 红线 | F26: V
B27: 不要用我的照片 | C27: =COUNTIF(学生档案!$V$3:$V$52,B27) | D27: =IF(COUNTA(学生档案!$C$3:$C$52)=0,"",C27/COUNTA(学生档案!$C$3:$C$52)) | E27: 不要用 = 红线 | F27: V
A28: 19 奖励 | B28: 画进上课漫画 | C28: =COUNTIF(学生档案!$W$3:$W$52,"*"&B28&"*") | D28: =IF(COUNTA(学生档案!$C$3:$C$52)=0,"",C28/COUNTA(学生档案!$C$3:$C$52)) | E28: 前3名抄进90-C5 | F28: W
B29: 卡通形象升级 | C29: =COUNTIF(学生档案!$W$3:$W$52,"*"&B29&"*") | D29: =IF(COUNTA(学生档案!$C$3:$C$52)=0,"",C29/COUNTA(学生档案!$C$3:$C$52)) | E29: 前3名抄进90-C5 | F29: W
B30: 加平时分 | C30: =COUNTIF(学生档案!$W$3:$W$52,"*"&B30&"*") | D30: =IF(COUNTA(学生档案!$C$3:$C$52)=0,"",C30/COUNTA(学生档案!$C$3:$C$52)) | E30: 前3名抄进90-C5 | F30: W
B31: 免一次作业 | C31: =COUNTIF(学生档案!$W$3:$W$52,"*"&B31&"*") | D31: =IF(COUNTA(学生档案!$C$3:$C$52)=0,"",C31/COUNTA(学生档案!$C$3:$C$52)) | E31: 前3名抄进90-C5 | F31: W
B32: 全班表扬 | C32: =COUNTIF(学生档案!$W$3:$W$52,"*"&B32&"*") | D32: =IF(COUNTA(学生档案!$C$3:$C$52)=0,"",C32/COUNTA(学生档案!$C$3:$C$52)) | E32: 前3名抄进90-C5 | F32: W
B33: 小零食 | C33: =COUNTIF(学生档案!$W$3:$W$52,"*"&B33&"*") | D33: =IF(COUNTA(学生档案!$C$3:$C$52)=0,"",C33/COUNTA(学生档案!$C$3:$C$52)) | E33: 前3名抄进90-C5 | F33: W
A34: 20 惩罚 | B34: 做成搞笑表情包 | C34: =COUNTIF(学生档案!$X$3:$X$52,"*"&B34&"*") | D34: =IF(COUNTA(学生档案!$C$3:$C$52)=0,"",C34/COUNTA(学生档案!$C$3:$C$52)) | E34: 前3名抄进90-C5 | F34: X
B35: 上台讲一道题 | C35: =COUNTIF(学生档案!$X$3:$X$52,"*"&B35&"*") | D35: =IF(COUNTA(学生档案!$C$3:$C$52)=0,"",C35/COUNTA(学生档案!$C$3:$C$52)) | E35: 前3名抄进90-C5 | F35: X
B36: 帮同学讲懂一道题 | C36: =COUNTIF(学生档案!$X$3:$X$52,"*"&B36&"*") | D36: =IF(COUNTA(学生档案!$C$3:$C$52)=0,"",C36/COUNTA(学生档案!$C$3:$C$52)) | E36: 前3名抄进90-C5 | F36: X
B37: 表演才艺30秒 | C37: =COUNTIF(学生档案!$X$3:$X$52,"*"&B37&"*") | D37: =IF(COUNTA(学生档案!$C$3:$C$52)=0,"",C37/COUNTA(学生档案!$C$3:$C$52)) | E37: 前3名抄进90-C5 | F37: X
B38: 罚做一道题 | C38: =COUNTIF(学生档案!$X$3:$X$52,"*"&B38&"*") | D38: =IF(COUNTA(学生档案!$C$3:$C$52)=0,"",C38/COUNTA(学生档案!$C$3:$C$52)) | E38: 前3名抄进90-C5 | F38: X
A40: 已填人数 | C40: =COUNTA(学生档案!$C$3:$C$52)
A41: 第18题红线人数 | C41: =COUNTIF(学生档案!$V$3:$V$52,"不要用我的照片")

Sheet 企业微信飞书字段
A1: 学校都有企业微信就用企业微信。飞书可以不用。「是否建」=否 的不要建题。字段标题一字不差。说明粘到该题备注里，学生才看得懂。
A2: 序号 | B2: 是否在企业微信建 | C2: 题型 | D2: 字段标题（一字不差） | E2: 选项（按／拆开粘） | F2: 必填 | G2: 发给学生看的说明（粘到题目备注） | H2: 老师自己看（不要贴进收集表）
A3: 1 | B3: 否（企业微信已有/纸质才要） | C3: 简答 | D3: 班级 | E3: （自由写） | F3: 选填 | H3: 企业微信不建。一个班一张表，导出后你在档案表 A 列往下填班级名。
A4: 2 | B4: 是 | C4: 简答 | D4: 学号 | E4: （自由写） | F4: 必填 | G4: 填你的学号，一定要填对。 | H4: 企业微信没有学号，必须建。后面文件名、积分、紫色列全靠这一列对上人。
A5: 3 | B5: 否（企业微信已有/纸质才要） | C5: 简答 | D5: 姓名 | E5: （自由写） | F5: 选填 | H5: 企业微信不建。导出后把「提交者」整列复制到「姓名」。
A6: 4 | B6: 是 | C6: 简答 | D6: 宿舍 | E6: （自由写） | F6: 选填 | G6: 选填。写几栋几号就行，比如 3-201。没有就空着。 | H6: 分组时「能同宿舍就同宿舍」，不是按宿舍整组切。不要把这句贴给学生。
A7: 5 | B7: 是 | C7: 单选 | D7: 1_以前接触过会计吗 | E7: 完全没有 ／ 听说过没学过 ／ 家里有人做会计 ／ 自己学过一点 | F7: 必填 | G7: 如实选。没有接触过很正常，没有对错。 | H7: 【别贴给学生】分组用：每组至少放一个选「完全没有」的。
A8: 6 | B8: 是 | C8: 单选 | D8: 2_自己数学怎么样 | E8: 还不错 ／ 一般 ／ 比较吃力 ／ 看到数字就头大 | F8: 必填 | G8: 如实选，没有对错。 | H8: 【别贴给学生】分组用：每组至少放一个选「还不错」的。
A9: 7 | B9: 是 | C9: 多选 | D9: 3_希望这门课怎么上 | E9: 多做游戏比赛 ／ 多讲实际案例 ／ 多动手实训 ／ 讲慢一点细一点 ／ 多用视频动画 ／ 多小组讨论 | F9: 选填 | G9: 可多选。你希望这门课怎么上，按真实想法勾。 | H9: 【别贴给学生】「多做游戏比赛」超过七成，网页工具要给足时间。
A10: 8 | B10: 是 | C10: 简答 | D10: 4_最担心这门课什么 | E10: （自由写） | F10: 选填 | G10: 随便写。比如怕算数、怕被提问、怕跟不上。没有就写「没有」。 | H10: 【别贴给学生】第二节课念几条匿名的。不当众点名。
A11: 9 | B11: 是 | C11: 单选 | D11: 5_上课最想看到哪个动画 | E11: 蜡笔小新 ／ 哆啦A梦 ／ 喜羊羊与灰太狼 | F11: 必填 | G11: 上课投影上会用动画片里的人物来举例。选一个你想看到的就行。 | H11: 【别贴给学生】最高票=班底动画。不要说「第7周起换」。
A12: 10 | B12: 是 | C12: 简答 | D12: 6_还喜欢哪个动画 | E12: （自由写） | F12: 选填 | G12: 没有就空着。 | H12: 【别贴给学生】个人出镜、合照优先用这个；空着就用第5题。
A13: 11 | B13: 是 | C13: 简答 | D13: 7_喜欢的明星或主播 | E13: （自由写） | F13: 选填 | G13: 没有就空着。 | H13: 【别贴给学生】项目结束合照可能会用。
A14: 12 | B14: 是 | C14: 简答 | D14: 8_外号是什么谁起的 | E14: （自由写） | F14: 选填 | G14: 没有就写「没有」。想不出来可以问旁边的人。 | H14: 【别贴给学生】后面画卡通时用。
A15: 13 | B15: 是 | C15: 简答 | D15: 9_口头禅 | E15: （自由写） | F15: 选填 | G15: 没有就写「没有」。 | H15: 【别贴给学生】画卡通时用。
A16: 14 | B16: 是 | C16: 简答 | D16: 10_小动作或小习惯 | E16: （自由写） | F16: 选填 | G16: 比如转笔、翘椅子、挠头。没有就写「没有」。 | H16: 【别贴给学生】画卡通时用。
A17: 15 | B17: 是 | C17: 简答 | D17: 11_最怕上课被问到什么 | E17: （自由写） | F17: 选填 | G17: 老师不会当众念出来。没有就写「没有」。 | H17: 【别贴给学生】避开雷区，不当众念。
... A27: 25 | B27: 是 | C27: 简答 | D27: 21_想对老师说的话 | E27: （自由写） | F27: 选填 | G27: 选填。老师私下看，不会当众念。 | H27: 【别贴给学生】私下看。
A28: 26 | B28: 否（企业微信已有/纸质才要） | C28: 日期 | D28: 填表日期 | E28: （自由写） | F28: 选填 | H28: 企业微信不建，有提交时间。纸质才写。
A29: 27 | B29: 否（企业微信已有/纸质才要） | C29: 简答 | D29: 本人签名 | E29: （自由写） | F29: 选填 | H29: 企业微信不建。纸质打印才手写。电子签名没有额外用处，提交者就是本人。
A31: 收集表最上面的「表单说明」整段复制（学生打开第一眼看到的）
A32: 这不是考试，没有标准答案。学号一定要填对。看不懂的题按字面选就行。
A34: 导出以后怎么贴进「学生档案」
A35: 1. 收集表右上角 → 导出 Excel。
A36: 2. 最左「提交者」整列复制到档案表「姓名」；「提交时间」丢掉。
A37: 3. 「学号」和 1_ 开头的题，按列名对到「学生档案」，整列粘贴。不要整表硬贴。
A38: 4. 班级：一个班一张表，档案表 A 列自己往下填。
A39: 5. 「本人签名」「填表日期」企业微信里没有，也不用贴。纸质才用。
A40: 6. 紫色 T_ 列一个都不要贴。贴完学号和第18题，它们自己会亮。
A41: 7. 发给学生看的说明，只复制本表绿色/白色「发给学生看的说明」列。橙色「老师自己看」列不要贴进收集表。

Sheet 分组怎么做
A1: 问卷贴进「学生档案」之后再来。现在左边空着、F 列没有标签，正常——标签是贴完第1题第2题才自动打的，学期一开始没有。 这张表不会自动分组。你只填 G 列（蓝色下拉）。不要让学委分组，学委会把熟人放一起。学委只帮核对宿舍号。 填法：先把 F 列「种子-数学」每人分到不同组 → 再把「零基础」每人分到不同组 → 「需帮扶」跟着种子走 → 剩下的人往人少的组填。同宿舍能一起就一起。 填完看右边：每组「种子」不能是 0，「零基础」不能是 0。上课说一句即可：你们这组叫出纳组，管钱的。不用讲岗位课。桌签 90-C10。
A2: 学号 | B2: 姓名 | C2: 宿舍 | D2: 接触过会计吗 | E2: 数学 | F2: 标签（自动） | G2: 就填这一列↓分到哪组 | H2: 备注 | J2: 组名 | K2: 人数 | L2: 种子 | M2: 零基础
A3: =IF(学生档案!B3="","",学生档案!B3) | B3: =IF(学生档案!C3="","",学生档案!C3) | C3: =IF(学生档案!D3="","",学生档案!D3) | D3: =IF(学生档案!E3="","",学生档案!E3) | E3: =IF(学生档案!F3="","",学生档案!F3) | F3: =IF(B3="","",IF(TRIM(E3)="还不错","种子-数学",IF(TRIM(D3)="完全没有","零基础",IF(TRIM(E3)="看到数字就头大","需帮扶","普通")))) | J3: 出纳组 | K3: =COUNTIF($G$3:$G$52,J3) | L3: =COUNTIFS($G$3:$G$52,J3,$F$3:$F$52,"种子-数学") | M3: =COUNTIFS($G$3:$G$52,J3,$F$3:$F$52,"零基础")
A4: =IF(学生档案!B4="","",学生档案!B4) | B4: =IF(学生档案!C4="","",学生档案!C4) | C4: =IF(学生档案!D4="","",学生档案!D4) | D4: =IF(学生档案!E4="","",学生档案!E4) | E4: =IF(学生档案!F4="","",学生档案!F4) | F4: =IF(B4="","",IF(TRIM(E4)="还不错","种子-数学",IF(TRIM(D4)="完全没有","零基础",IF(TRIM(E4)="看到数字就头大","需帮扶","普通")))) | J4: 记账组 | K4: =COUNTIF($G$3:$G$52,J4) | L4: =COUNTIFS($G$3:$G$52,J4,$F$3:$F$52,"种子-数学") | M4: =COUNTIFS($G$3:$G$52,J4,$F$3:$F$52,"零基础")
A5: =IF(学生档案!B5="","",学生档案!B5) | B5: =IF(学生档案!C5="","",学生档案!C5) | C5: =IF(学生档案!D5="","",学生档案!D5) | D5: =IF(学生档案!E5="","",学生档案!E5) | E5: =IF(学生档案!F5="","",学生档案!F5) | F5: =IF(B5="","",IF(TRIM(E5)="还不错","种子-数学",IF(TRIM(D5)="完全没有","零基础",IF(TRIM(E5)="看到数字就头大","需帮扶","普通")))) | J5: 成本组 | K5: =COUNTIF($G$3:$G$52,J5) | L5: =COUNTIFS($G$3:$G$52,J5,$F$3:$F$52,"种子-数学") | M5: =COUNTIFS($G$3:$G$52,J5,$F$3:$F$52,"零基础")
A6: =IF(学生档案!B6="","",学生档案!B6) | B6: =IF(学生档案!C6="","",学生档案!C6) | C6: =IF(学生档案!D6="","",学生档案!D6) | D6: =IF(学生档案!E6="","",学生档案!E6) | E6: =IF(学生档案!F6="","",学生档案!F6) | F6: =IF(B6="","",IF(TRIM(E6)="还不错","种子-数学",IF(TRIM(D6)="完全没有","零基础",IF(TRIM(E6)="看到数字就头大","需帮扶","普通")))) | J6: 审核组 | K6: =COUNTIF($G$3:$G$52,J6) | L6: =COUNTIFS($G$3:$G$52,J6,$F$3:$F$52,"种子-数学") | M6: =COUNTIFS($G$3:$G$52,J6,$F$3:$F$52,"零基础")
A7: =IF(学生档案!B7="","",学生档案!B7) | B7: =IF(学生档案!C7="","",学生档案!C7) | C7: =IF(学生档案!D7="","",学生档案!D7) | D7: =IF(学生档案!E7="","",学生档案!E7) | E7: =IF(学生档案!F7="","",学生档案!F7) | F7: =IF(B7="","",IF(TRIM(E7)="还不错","种子-数学",IF(TRIM(D7)="完全没有","零基础",IF(TRIM(E7)="看到数字就头大","需帮扶","普通")))) | J7: 仓管组 | K7: =COUNTIF($G$3:$G$52,J7) | L7: =COUNTIFS($G$3:$G$52,J7,$F$3:$F$52,"种子-数学") | M7: =COUNTIFS($G$3:$G$52,J7,$F$3:$F$52,"零基础")
A8: =IF(学生档案!B8="","",学生档案!B8) | B8: =IF(学生档案!C8="","",学生档案!C8) | C8: =IF(学生档案!D8="","",学生档案!D8) | D8: =IF(学生档案!E8="","",学生档案!E8) | E8: =IF(学生档案!F8="","",学生档案!F8) | F8: =IF(B8="","",IF(TRIM(E8)="还不错","种子-数学",IF(TRIM(D8)="完全没有","零基础",IF(TRIM(E8)="看到数字就头大","需帮扶","普通")))) | J8: 报表组 | K8: =COUNTIF($G$3:$G$52,J8) | L8: =COUNTIFS($G$3:$G$52,J8,$F$3:$F$52,"种子-数学") | M8: =COUNTIFS($G$3:$G$52,J8,$F$3:$F$52,"零基础")
A9: =IF(学生档案!B9="","",学生档案!B9) | B9: =IF(学生档案!C9="","",学生档案!C9) | C9: =IF(学生档案!D9="","",学生档案!D9) | D9: =IF(学生档案!E9="","",学生档案!E9) | E9: =IF(学生档案!F9="","",学生档案!F9) | F9: =IF(B9="","",IF(TRIM(E9)="还不错","种子-数学",IF(TRIM(D9)="完全没有","零基础",IF(TRIM(E9)="看到数字就头大","需帮扶","普通"))))
A10: =IF(学生档案!B10="","",学生档案!B10) | B10: =IF(学生档案!C10="","",学生档案!C10) | C10: =IF(学生档案!D10="","",学生档案!D10) | D10: =IF(学生档案!E10="","",学生档案!E10) | E10: =IF(学生档案!F10="","",学生档案!F10) | F10: =IF(B10="","",IF(TRIM(E10)="还不错","种子-数学",IF(TRIM(D10)="完全没有","零基础",IF(TRIM(E10)="看到数字就头大","需帮扶","普通")))) | J10: 人数差超过 2，或某组种子=0 / 零基础=0，就再调。
A11: =IF(学生档案!B11="","",学生档案!B11) | B11: =IF(学生档案!C11="","",学生档案!C11) | C11: =IF(学生档案!D11="","",学生档案!D11) | D11: =IF(学生档案!E11="","",学生档案!E11) | E11: =IF(学生档案!F11="","",学生档案!F11) | F11: =IF(B11="","",IF(TRIM(E11)="还不错","种子-数学",IF(TRIM(D11)="完全没有","零基础",IF(TRIM(E11)="看到数字就头大","需帮扶","普通"))))
A12: =IF(学生档案!B12="","",学生档案!B12) | B12: =IF(学生档案!C12="","",学生档案!C12) | C12: =IF(学生档案!D12="","",学生档案!D12) | D12: =IF(学生档案!E12="","",学生档案!E12) | E12: =IF(学生档案!F12="","",学生档案!F12) | F12: =IF(B12="","",IF(TRIM(E12)="还不错","种子-数学",IF(TRIM(D12)="完全没有","零基础",IF(TRIM(E12)="看到数字就头大","需帮扶","普通"))))
A13: =IF(学生档案!B13="","",学生档案!B13) | B13: =IF(学生档案!C13="","",学生档案!C13) | C13: =IF(学生档案!D13="","",学生档案!D13) | D13: =IF(学生档案!E13="","",学生档案!E13) | E13: =IF(学生档案!F13="","",学生档案!F13) | F13: =IF(B13="","",IF(TRIM(E13)="还不错","种子-数学",IF(TRIM(D13)="完全没有","零基础",IF(TRIM(E13)="看到数字就头大","需帮扶","普通"))))
A14: =IF(学生档案!B14="","",学生档案!B14) | B14: =IF(学生档案!C14="","",学生档案!C14) | C14: =IF(学生档案!D14="","",学生档案!D14) | D14: =IF(学生档案!E14="","",学生档案!E14) | E14: =IF(学生档案!F14="","",学生档案!F14) | F14: =IF(B14="","",IF(TRIM(E14)="还不错","种子-数学",IF(TRIM(D14)="完全没有","零基础",IF(TRIM(E14)="看到数字就头大","需帮扶","普通"))))
A15: =IF(学生档案!B15="","",学生档案!B15) | B15: =IF(学生档案!C15="","",学生档案!C15) | C15: =IF(学生档案!D15="","",学生档案!D15) | D15: =IF(学生档案!E15="","",学生档案!E15) | E15: =IF(学生档案!F15="","",学生档案!F15) | F15: =IF(B15="","",IF(TRIM(E15)="还不错","种子-数学",IF(TRIM(D15)="完全没有","零基础",IF(TRIM(E15)="看到数字就头大","需帮扶","普通"))))
A16: =IF(学生档案!B16="","",学生档案!B16) | B16: =IF(学生档案!C16="","",学生档案!C16) | C16: =IF(学生档案!D16="","",学生档案!D16) | D16: =IF(学生档案!E16="","",学生档案!E16) | E16: =IF(学生档案!F16="","",学生档案!F16) | F16: =IF(B16="","",IF(TRIM(E16)="还不错","种子-数学",IF(TRIM(D16)="完全没有","零基础",IF(TRIM(E16)="看到数字就头大","需帮扶","普通"))))
A17: =IF(学生档案!B17="","",学生档案!B17) | B17: =IF(学生档案!C17="","",学生档案!C17) | C17: =IF(学生档案!D17="","",学生档案!D17) | D17: =IF(学生档案!E17="","",学生档案!E17) | E17: =IF(学生档案!F17="","",学生档案!F17) | F17: =IF(B17="","",IF(TRIM(E17)="还不错","种子-数学",IF(TRIM(D17)="完全没有","零基础",IF(TRIM(E17)="看到数字就头大","需帮扶","普通"))))
A18: =IF(学生档案!B18="","",学生档案!B18) | B18: =IF(学生档案!C18="","",学生档案!C18) | C18: =IF(学生档案!D18="","",学生档案!D18) | D18: =IF(学生档案!E18="","",学生档案!E18) | E18: =IF(学生档案!F18="","",学生档案!F18) | F18: =IF(B18="","",IF(TRIM(E18)="还不错","种子-数学",IF(TRIM(D18)="完全没有","零基础",IF(TRIM(E18)="看到数字就头大","需帮扶","普通"))))
A19: =IF(学生档案!B19="","",学生档案!B19) | B19: =IF(学生档案!C19="","",学生档案!C19) | C19: =IF(学生档案!D19="","",学生档案!D19) | D19: =IF(学生档案!E19="","",学生档案!E19) | E19: =IF(学生档案!F19="","",学生档案!F19) | F19: =IF(B19="","",IF(TRIM(E19)="还不错","种子-数学",IF(TRIM(D19)="完全没有","零基础",IF(TRIM(E19)="看到数字就头大","需帮扶","普通"))))
A20: =IF(学生档案!B20="","",学生档案!B20) | B20: =IF(学生档案!C20="","",学生档案!C20) | C20: =IF(学生档案!D20="","",学生档案!D20) | D20: =IF(学生档案!E20="","",学生档案!E20) | E20: =IF(学生档案!F20="","",学生档案!F20) | F20: =IF(B20="","",IF(TRIM(E20)="还不错","种子-数学",IF(TRIM(D20)="完全没有","零基础",IF(TRIM(E20)="看到数字就头大","需帮扶","普通"))))
A21: =IF(学生档案!B21="","",学生档案!B21) | B21: =IF(学生档案!C21="","",学生档案!C21) | C21: =IF(学生档案!D21="","",学生档案!D21) | D21: =IF(学生档案!E21="","",学生档案!E21) | E21: =IF(学生档案!F21="","",学生档案!F21) | F21: =IF(B21="","",IF(TRIM(E21)="还不错","种子-数学",IF(TRIM(D21)="完全没有","零基础",IF(TRIM(E21)="看到数字就头大","需帮扶","普通"))))
A22: =IF(学生档案!B22="","",学生档案!B22) | B22: =IF(学生档案!C22="","",学生档案!C22) | C22: =IF(学生档案!D22="","",学生档案!D22) | D22: =IF(学生档案!E22="","",学生档案!E22) | E22: =IF(学生档案!F22="","",学生档案!F22) | F22: =IF(B22="","",IF(TRIM(E22)="还不错","种子-数学",IF(TRIM(D22)="完全没有","零基础",IF(TRIM(E22)="看到数字就头大","需帮扶","普通"))))
... A52: =IF(学生档案!B52="","",学生档案!B52) | B52: =IF(学生档案!C52="","",学生档案!C52) | C52: =IF(学生档案!D52="","",学生档案!D52) | D52: =IF(学生档案!E52="","",学生档案!E52) | E52: =IF(学生档案!F52="","",学生档案!F52) | F52: =IF(B52="","",IF(TRIM(E52)="还不错","种子-数学",IF(TRIM(D52)="完全没有","零基础",IF(TRIM(E52)="看到数字就头大","需帮扶","普通"))))
A54: 你具体做什么（贴完学生档案之后）
A55: 第 0 步 现在先别动。问卷还没收回来，左边空着是正常的。收回来并贴进「学生档案」之后，这张表左边会自动出现全班名单，F 列自动打标签。
A56: 第 1 步 只看 F 列（紫色，自动的）。四种标签：种子-数学＝第2题选了「还不错」；零基础＝第1题选了「完全没有」；需帮扶＝第2题选了「看到数字就头大」；普通＝其他人。
A57: 第 2 步 只填 G 列。点蓝色格子，下拉选出纳组 / 记账组 / 成本组 / 审核组 / 仓管组 / 报表组。先筛「种子-数学」，6 个人分别放进 6 个组（一人一组）。
A58: 第 3 步 再筛「零基础」，也是 6 个组每个组放 1 个。然后「需帮扶」尽量跟种子同一组（种子能带）。剩下的人往人数少的组填。同宿舍能分一起就一起，不要为了同宿舍把种子拆走。
A59: 第 4 步 看右边人数表。人数差不要超过 2；「种子」列不能是 0；「零基础」列不能是 0。哪组是 0，把人调一下。
A60: 第 5 步 打印 90-C10 岗位桌签，上课放到对应桌上。跟学生只说：你们这组今天是出纳组。不要说「种子」「零基础」「标签」。
A61: 分组只用在三件事：打地鼠按组上台；填凭证组内互审（制单和审核不能同一人）；静默十五分四人讨论。举册子、点名加分是个人的，不要为了分组而分组。每个项目结束可以把桌签轮换（出纳这周当审核），别让人整个学期都是仓管。
A63: 举个假人例子（只演示怎么填 G 列，不是你班上的人）
A64: 假设 F 列打出：王磊＝种子-数学，陈静＝种子-数学，刘洋＝零基础，赵敏＝零基础，周杰＝需帮扶，孙丽＝普通（和王磊同宿舍）。
A65: G 列这样填：王磊 → 出纳组；陈静 → 记账组。（两个种子先拆开）
A66: 刘洋 → 出纳组（和王磊一组，种子带零基础）；赵敏 → 记账组（和陈静一组）。
... A80: 出纳组不用专门讲。桌签上已有「管钱的。库存现金、银行存款从这组过。」上课说：你们这组叫出纳组，管钱的，以后填收付款从你们这过。现在先坐一起。记账组、审核组同理，桌签上各有一行。

Sheet 紫色T列怎么用
A1: 紫色 T_ 列怎么用 —— 现在没有图片，也没有分数
A2: 企业微信导出里不会、也不该出现这几列。你把学生填的题贴进左边（班级到签名），右边紫色格子自己会亮。亮出来的「2401006.png」不是文件，是以后存图片用的名字；亮出来的 0 分不是坏了，是还没上课。
A3: 列名 | B3: 谁填 | C3: 格子里会出现什么 | D3: 你要做什么
A4: T_卡通形象文件名 | B4: 公式，不用填 | C4: 学号 2401006 → 格子里写出 2401006.png。电脑里没有这个文件。 | D4: 现在什么都不用做。以后真的开始画卡通头像了，在电脑里建一个文件夹（比如「会计课卡通头像」），保存时文件名就用这一格的字。第18题选「不要用我的照片」的人，可以不画他的脸，这一格空着或改个不含照片的名字就行。
A5: T_累计积分 | B5: 公式，不用填 | C5: 从「每周积分」按学号把各周加总。现在是 0。 | D5: 你不用填这一列。你要做的是每周往「每周积分」贴一次本周分数（见「怎么用」第二节）。贴了，这里才会涨。评奖、换免点名卡看它。
A6: T_当前等级 | B6: 公式，不用填 | C6: 按累计分：15 出纳 / 30 记账 / 50 主管 / 80 CFO。现在是实习生。 | D6: 不用管。以后漫画换装才用。分不够就一直是实习生。
A7: T_红线_形象 | B7: 公式，不用填 | C7: 读第18题。选「不要用我的照片」或「只给我自己看」→ ★形象不可公开。 | D7: 每周要画人上投影之前扫一眼。带星号的换人。不是企业微信的题。
A8: T_备注 | B8: 你手写 | C8: 空的，等你写。 | D8: 班长、人缘好（第一次惩罚找他）、缺课、特殊情况。
A10: 举个完整例子（人是假的）
A11: 企业微信收回来：学号 2401006，姓名 刘思远，第18题「不要用我的照片」，第16题「这次先不参加」。
A12: 你只把学号、姓名、第16题、第18题等学生填的列贴进「学生档案」。不要贴紫色列。
A13: 贴完以后这一行紫色格子自己变成：文件名 2401006.png（现在仍然没有这张图）；红线 ★形象不可公开；积分 0（还没上课）。
A14: 以后每周出镜、项目结束合照，看到星号就跳过他。积分该加还加，换免点名卡不受影响。电脑里依然没有 2401006.png，除非你后来真的画了一张。
A15: 所以：企业微信负责「学生说了什么」；紫色列负责「老师据此自动判断什么」。两套东西，靠学号这一列焊在一起。

Sheet 选项库
A1: 下拉选项库（不要改文字）
A2: 1_以前接触过会计吗 | B2: 2_自己数学怎么样 | C2: 3_希望这门课怎么上 | D2: 5_上课最想看到哪个动画 | E2: 16_想不想和喜欢的卡通同框 | F2: 18_能用你的照片画卡通吗 | G2: 19_什么奖励对你有用 | H2: 20_哪种惩罚你能接受还觉得好玩 | I2: 作业分档 | J2: 岗位组
A3: 完全没有 | B3: 还不错 | C3: 多做游戏比赛 | D3: 蜡笔小新 | E3: 想，和我喜欢的角色同框 | F3: 随便用 | G3: 画进上课漫画 | H3: 做成搞笑表情包 | I3: 0 | J3: 出纳组
A4: 听说过没学过 | B4: 一般 | C4: 多讲实际案例 | D4: 哆啦A梦 | E4: 可以试试 | F4: 可以但别画太丑 | G4: 卡通形象升级 | H4: 上台讲一道题 | I4: 2 | J4: 记账组
A5: 家里有人做会计 | B5: 比较吃力 | C5: 多动手实训 | D5: 喜羊羊与灰太狼 | E5: 先看别人的，先别画我 | F5: 只给我自己看 | G5: 加平时分 | H5: 帮同学讲懂一道题 | I5: 5 | J5: 成本组
A6: 自己学过一点 | B6: 看到数字就头大 | C6: 讲慢一点细一点 | E6: 这次先不参加 | F6: 不要用我的照片 | G6: 免一次作业 | H6: 表演才艺30秒 | J6: 审核组
C7: 多用视频动画 | G7: 全班表扬 | H7: 罚做一道题 | J7: 仓管组
C8: 多小组讨论 | G8: 小零食 | J8: 报表组
